{"nomor":77,"nama":"المرسلٰت","namaLatin":"Al-Mursalat","tempatTurun":"Mekah","jumlahAyat":50,"ayat":[{"nomor":1,"arab":"وَالْمُرْسَلٰتِ عُرْفًاۙ","terjemah":"Demi (malaikat-malaikat) yang diutus untuk membawa kebaikan,"},{"nomor":2,"arab":"فَالْعٰصِفٰتِ عَصْفًاۙ","terjemah":"dan (malaikat-malaikat) yang terbang dengan kencangnya,"},{"nomor":3,"arab":"وَّالنّٰشِرٰتِ نَشْرًاۙ","terjemah":"dan (malaikat-malaikat) yang menyebarkan (rahmat Allah) dengan seluas-luasnya,"},{"nomor":4,"arab":"فَالْفٰرِقٰتِ فَرْقًاۙ","terjemah":"dan (malaikat-malaikat) yang membedakan (antara yang baik dan yang buruk) dengan sejelas-jelasnya,"},{"nomor":5,"arab":"فَالْمُلْقِيٰتِ ذِكْرًاۙ","terjemah":"dan (malaikat-malaikat) yang menyampaikan wahyu,"},{"nomor":6,"arab":"عُذْرًا اَوْ نُذْرًاۙ","terjemah":"untuk menolak alasan-alasan atau memberi peringatan."},{"nomor":7,"arab":"اِنَّمَا تُوْعَدُوْنَ لَوَاقِعٌۗ","terjemah":"Sungguh, apa yang dijanjikan kepadamu pasti terjadi."},{"nomor":8,"arab":"فَاِذَا النُّجُوْمُ طُمِسَتْۙ","terjemah":"Maka apabila bintang-bintang dihapuskan,"},{"nomor":9,"arab":"وَاِذَا السَّمَاۤءُ فُرِجَتْۙ","terjemah":"dan apabila langit terbelah,"},{"nomor":10,"arab":"وَاِذَا الْجِبَالُ نُسِفَتْۙ","terjemah":"dan apabila gunung-gunung dihancurkan menjadi debu,"},{"nomor":11,"arab":"وَاِذَا الرُّسُلُ اُقِّتَتْۗ","terjemah":"dan apabila rasul-rasul telah ditetapkan waktunya."},{"nomor":12,"arab":"لِاَيِّ يَوْمٍ اُجِّلَتْۗ","terjemah":"(Niscaya dikatakan kepada mereka), “Sampai hari apakah ditangguhkan (azab orang-orang kafir itu)?”"},{"nomor":13,"arab":"لِيَوْمِ الْفَصْلِۚ","terjemah":"Sampai hari keputusan."},{"nomor":14,"arab":"وَمَآ اَدْرٰىكَ مَا يَوْمُ الْفَصْلِۗ","terjemah":"Dan tahukah kamu apakah hari ke-putusan itu?"},{"nomor":15,"arab":"وَيْلٌ يَّوْمَىِٕذٍ لِّلْمُكَذِّبِيْنَ ","terjemah":"Celakalah pada hari itu, bagi mereka yang mendustakan (kebenaran)."},{"nomor":16,"arab":"اَلَمْ نُهْلِكِ الْاَوَّلِيْنَۗ","terjemah":"Bukankah telah Kami binasakan orang-orang yang dahulu?"},{"nomor":17,"arab":"ثُمَّ نُتْبِعُهُمُ الْاٰخِرِيْنَ ","terjemah":"Lalu Kami susulkan (azab Kami terhadap) orang-orang yang datang kemudian."},{"nomor":18,"arab":"كَذٰلِكَ نَفْعَلُ بِالْمُجْرِمِيْنَ ","terjemah":"Demikianlah Kami perlakukan orang-orang yang berdosa."},{"nomor":19,"arab":"وَيْلٌ يَّوْمَىِٕذٍ لِّلْمُكَذِّبِيْنَ ","terjemah":"Celakalah pada hari itu, bagi mereka yang mendustakan (kebenaran)."},{"nomor":20,"arab":"اَلَمْ نَخْلُقْكُّمْ مِّنْ مَّاۤءٍ مَّهِيْنٍۙ","terjemah":"Bukankah Kami menciptakan kamu dari air yang hina (mani),"},{"nomor":21,"arab":"فَجَعَلْنٰهُ فِيْ قَرَارٍ مَّكِيْنٍ","terjemah":"kemudian Kami letakkan ia dalam tempat yang kokoh (rahim),"},{"nomor":22,"arab":"اِلٰى قَدَرٍ مَّعْلُوْمٍۙ","terjemah":"sampai waktu yang ditentukan,"},{"nomor":23,"arab":"فَقَدَرْنَاۖ فَنِعْمَ الْقٰدِرُوْنَ ","terjemah":"lalu Kami tentukan (bentuknya), maka (Kamilah) sebaik-baik yang menentukan."},{"nomor":24,"arab":"وَيْلٌ يَّوْمَىِٕذٍ لِّلْمُكَذِّبِيْنَ ","terjemah":"Celakalah pada hari itu, bagi mereka yang mendustakan (kebenaran)."},{"nomor":25,"arab":"اَلَمْ نَجْعَلِ الْاَرْضَ كِفَاتًاۙ","terjemah":"Bukankah Kami jadikan bumi untuk (tempat) berkumpul,"},{"nomor":26,"arab":"اَحْيَاۤءً وَّاَمْوَاتًاۙ","terjemah":"bagi yang masih hidup dan yang sudah mati?"},{"nomor":27,"arab":"وَّجَعَلْنَا فِيْهَا رَوَاسِيَ شٰمِخٰتٍ وَّاَسْقَيْنٰكُمْ مَّاۤءً فُرَاتًاۗ","terjemah":"Dan Kami jadikan padanya gunung-gunung yang tinggi, dan Kami beri minum kamu dengan air tawar?"},{"nomor":28,"arab":"وَيْلٌ يَّوْمَىِٕذٍ لِّلْمُكَذِّبِيْنَ ","terjemah":"Celakalah pada hari itu, bagi mereka yang mendustakan (kebenaran)."},{"nomor":29,"arab":"اِنْطَلِقُوْٓا اِلٰى مَا كُنْتُمْ بِهٖ تُكَذِّبُوْنَۚ","terjemah":"(Akan dikatakan), “Pergilah kamu mendapatkan apa (azab) yang dahulu kamu dustakan."},{"nomor":30,"arab":"اِنْطَلِقُوْٓا اِلٰى ظِلٍّ ذِيْ ثَلٰثِ شُعَبٍ ","terjemah":"Pergilah kamu mendapatkan naungan (asap api neraka) yang mempunyai tiga cabang, "},{"nomor":31,"arab":"لَا ظَلِيْلٍ وَّلَا يُغْنِيْ مِنَ اللَّهَبِۗ","terjemah":"yang tidak melindungi dan tidak pula menolak nyala api neraka.” "},{"nomor":32,"arab":"اِنَّهَا تَرْمِيْ بِشَرَرٍ كَالْقَصْرِۚ","terjemah":"Sungguh, (neraka) itu menyemburkan bunga api (sebesar dan setinggi) istana, "},{"nomor":33,"arab":"كَاَنَّهٗ جِمٰلَتٌ صُفْرٌۗ","terjemah":"seakan-akan iring-iringan unta yang kuning."},{"nomor":34,"arab":"وَيْلٌ يَّوْمَىِٕذٍ لِّلْمُكَذِّبِيْنَ ","terjemah":"Celakalah pada hari itu, bagi mereka yang mendustakan (kebenaran). "},{"nomor":35,"arab":"هٰذَا يَوْمُ لَا يَنْطِقُوْنَۙ","terjemah":"Inilah hari, saat mereka tidak dapat berbicara, "},{"nomor":36,"arab":"وَلَا يُؤْذَنُ لَهُمْ فَيَعْتَذِرُوْنَ ","terjemah":"dan tidak diizinkan kepada mereka mengemukakan alasan agar mereka dimaafkan. "},{"nomor":37,"arab":"وَيْلٌ يَّوْمَىِٕذٍ لِّلْمُكَذِّبِيْنَ ","terjemah":"Celakalah pada hari itu, bagi mereka yang mendustakan (kebenaran). "},{"nomor":38,"arab":"هٰذَا يَوْمُ الْفَصْلِ جَمَعْنٰكُمْ وَالْاَوَّلِيْنَ ","terjemah":"Inilah hari keputusan; (pada hari ini) Kami kumpulkan kamu dan orang-orang yang terdahulu. "},{"nomor":39,"arab":"فَاِنْ كَانَ لَكُمْ كَيْدٌ فَكِيْدُوْنِ ","terjemah":"Maka jika kamu punya tipu daya, maka lakukanlah (tipu daya) itu terhadap-Ku. "},{"nomor":40,"arab":"وَيْلٌ يَّوْمَىِٕذٍ لِّلْمُكَذِّبِيْنَ ࣖ ","terjemah":"Celakalah pada hari itu, bagi mereka yang mendustakan (kebenaran)."},{"nomor":41,"arab":"اِنَّ الْمُتَّقِيْنَ فِيْ ظِلٰلٍ وَّعُيُوْنٍۙ","terjemah":"Sungguh, orang-orang yang bertakwa berada dalam naungan (pepohonan surga yang teduh) dan (di sekitar) mata air, "},{"nomor":42,"arab":"وَّفَوَاكِهَ مِمَّا يَشْتَهُوْنَۗ","terjemah":"dan buah-buahan yang mereka sukai. "},{"nomor":43,"arab":"كُلُوْا وَاشْرَبُوْا هَنِيْۤـًٔا ۢبِمَا كُنْتُمْ تَعْمَلُوْنَ ","terjemah":"(Katakan kepada mereka), “Makan dan minumlah dengan rasa nikmat sebagai balasan dari apa yang telah kamu kerjakan.” "},{"nomor":44,"arab":"اِنَّا كَذٰلِكَ نَجْزِى الْمُحْسِنِيْنَ ","terjemah":"Sungguh, demikianlah Kami memberi balasan kepada orang-orang yang berbuat baik. "},{"nomor":45,"arab":"وَيْلٌ يَّوْمَىِٕذٍ لِّلْمُكَذِّبِيْنَ ","terjemah":"Celakalah pada hari itu, bagi mereka yang mendustakan (kebenaran). "},{"nomor":46,"arab":"كُلُوْا وَتَمَتَّعُوْا قَلِيْلًا اِنَّكُمْ مُّجْرِمُوْنَ ","terjemah":"(Katakan kepada orang-orang kafir), “Makan dan bersenang-senanglah kamu (di dunia) sebentar, sesungguhnya kamu orang-orang durhaka!”"},{"nomor":47,"arab":"وَيْلٌ يَّوْمَىِٕذٍ لِّلْمُكَذِّبِيْنَ ","terjemah":"Celakalah pada hari itu, bagi mereka yang mendustakan (kebenaran). "},{"nomor":48,"arab":"وَاِذَا قِيْلَ لَهُمُ ارْكَعُوْا لَا يَرْكَعُوْنَ ","terjemah":"Dan apabila dikatakan kepada mereka, “Rukuklah,” mereka tidak mau rukuk."},{"nomor":49,"arab":"وَيْلٌ يَّوْمَىِٕذٍ لِّلْمُكَذِّبِيْنَ ","terjemah":"Celakalah pada hari itu, bagi mereka yang mendustakan (kebenaran)! "},{"nomor":50,"arab":"فَبِاَيِّ حَدِيْثٍۢ بَعْدَهٗ يُؤْمِنُوْنَ ࣖ   ۔","terjemah":"Maka kepada ajaran manakah (selain Al-Qur'an) ini mereka akan beriman?"}]}