{"page":103,"juz":6,"lines":[{"n":1,"words":[{"t":"فَبِمَا","s":4,"a":155},{"t":"نَقْضِهِم","s":4,"a":155},{"t":"مِّيثَـٰقَهُمْ","s":4,"a":155},{"t":"وَكُفْرِهِم","s":4,"a":155},{"t":"بِـَٔايَـٰتِ","s":4,"a":155},{"t":"ٱللَّهِ","s":4,"a":155},{"t":"وَقَتْلِهِمُ","s":4,"a":155},{"t":"ٱلْأَنۢبِيَآءَ","s":4,"a":155}]},{"n":2,"words":[{"t":"بِغَيْرِ","s":4,"a":155},{"t":"حَقٍّۢ","s":4,"a":155},{"t":"وَقَوْلِهِمْ","s":4,"a":155},{"t":"قُلُوبُنَا","s":4,"a":155},{"t":"غُلْفٌۢ","s":4,"a":155},{"t":"ۚ","s":4,"a":155},{"t":"بَلْ","s":4,"a":155},{"t":"طَبَعَ","s":4,"a":155},{"t":"ٱللَّهُ","s":4,"a":155},{"t":"عَلَيْهَا","s":4,"a":155},{"t":"بِكُفْرِهِمْ","s":4,"a":155}]},{"n":3,"words":[{"t":"فَلَا","s":4,"a":155},{"t":"يُؤْمِنُونَ","s":4,"a":155},{"t":"إِلَّا","s":4,"a":155},{"t":"قَلِيلًۭا","s":4,"a":155},{"t":"وَبِكُفْرِهِمْ","s":4,"a":156},{"t":"وَقَوْلِهِمْ","s":4,"a":156},{"t":"عَلَىٰ","s":4,"a":156},{"t":"مَرْيَمَ","s":4,"a":156}]},{"n":4,"words":[{"t":"بُهْتَـٰنًا","s":4,"a":156},{"t":"عَظِيمًۭا","s":4,"a":156},{"t":"وَقَوْلِهِمْ","s":4,"a":157},{"t":"إِنَّا","s":4,"a":157},{"t":"قَتَلْنَا","s":4,"a":157},{"t":"ٱلْمَسِيحَ","s":4,"a":157},{"t":"عِيسَى","s":4,"a":157},{"t":"ٱبْنَ","s":4,"a":157},{"t":"مَرْيَمَ","s":4,"a":157}]},{"n":5,"words":[{"t":"رَسُولَ","s":4,"a":157},{"t":"ٱللَّهِ","s":4,"a":157},{"t":"وَمَا","s":4,"a":157},{"t":"قَتَلُوهُ","s":4,"a":157},{"t":"وَمَا","s":4,"a":157},{"t":"صَلَبُوهُ","s":4,"a":157},{"t":"وَلَـٰكِن","s":4,"a":157},{"t":"شُبِّهَ","s":4,"a":157},{"t":"لَهُمْ","s":4,"a":157},{"t":"ۚ","s":4,"a":157},{"t":"وَإِنَّ","s":4,"a":157},{"t":"ٱلَّذِينَ","s":4,"a":157}]},{"n":6,"words":[{"t":"ٱخْتَلَفُوا۟","s":4,"a":157},{"t":"فِيهِ","s":4,"a":157},{"t":"لَفِى","s":4,"a":157},{"t":"شَكٍّۢ","s":4,"a":157},{"t":"مِّنْهُ","s":4,"a":157},{"t":"ۚ","s":4,"a":157},{"t":"مَا","s":4,"a":157},{"t":"لَهُم","s":4,"a":157},{"t":"بِهِۦ","s":4,"a":157},{"t":"مِنْ","s":4,"a":157},{"t":"عِلْمٍ","s":4,"a":157},{"t":"إِلَّا","s":4,"a":157},{"t":"ٱتِّبَاعَ","s":4,"a":157},{"t":"ٱلظَّنِّ","s":4,"a":157},{"t":"ۚ","s":4,"a":157}]},{"n":7,"words":[{"t":"وَمَا","s":4,"a":157},{"t":"قَتَلُوهُ","s":4,"a":157},{"t":"يَقِينًۢا","s":4,"a":157},{"t":"بَل","s":4,"a":158},{"t":"رَّفَعَهُ","s":4,"a":158},{"t":"ٱللَّهُ","s":4,"a":158},{"t":"إِلَيْهِ","s":4,"a":158},{"t":"ۚ","s":4,"a":158},{"t":"وَكَانَ","s":4,"a":158},{"t":"ٱللَّهُ","s":4,"a":158},{"t":"عَزِيزًا","s":4,"a":158},{"t":"حَكِيمًۭا","s":4,"a":158}]},{"n":8,"words":[{"t":"وَإِن","s":4,"a":159},{"t":"مِّنْ","s":4,"a":159},{"t":"أَهْلِ","s":4,"a":159},{"t":"ٱلْكِتَـٰبِ","s":4,"a":159},{"t":"إِلَّا","s":4,"a":159},{"t":"لَيُؤْمِنَنَّ","s":4,"a":159},{"t":"بِهِۦ","s":4,"a":159},{"t":"قَبْلَ","s":4,"a":159},{"t":"مَوْتِهِۦ","s":4,"a":159},{"t":"ۖ","s":4,"a":159},{"t":"وَيَوْمَ","s":4,"a":159}]},{"n":9,"words":[{"t":"ٱلْقِيَـٰمَةِ","s":4,"a":159},{"t":"يَكُونُ","s":4,"a":159},{"t":"عَلَيْهِمْ","s":4,"a":159},{"t":"شَهِيدًۭا","s":4,"a":159},{"t":"فَبِظُلْمٍۢ","s":4,"a":160},{"t":"مِّنَ","s":4,"a":160},{"t":"ٱلَّذِينَ","s":4,"a":160},{"t":"هَادُوا۟","s":4,"a":160}]},{"n":10,"words":[{"t":"حَرَّمْنَا","s":4,"a":160},{"t":"عَلَيْهِمْ","s":4,"a":160},{"t":"طَيِّبَـٰتٍ","s":4,"a":160},{"t":"أُحِلَّتْ","s":4,"a":160},{"t":"لَهُمْ","s":4,"a":160},{"t":"وَبِصَدِّهِمْ","s":4,"a":160},{"t":"عَن","s":4,"a":160},{"t":"سَبِيلِ","s":4,"a":160},{"t":"ٱللَّهِ","s":4,"a":160}]},{"n":11,"words":[{"t":"كَثِيرًۭا","s":4,"a":160},{"t":"وَأَخْذِهِمُ","s":4,"a":161},{"t":"ٱلرِّبَوٰا۟","s":4,"a":161},{"t":"وَقَدْ","s":4,"a":161},{"t":"نُهُوا۟","s":4,"a":161},{"t":"عَنْهُ","s":4,"a":161},{"t":"وَأَكْلِهِمْ","s":4,"a":161},{"t":"أَمْوَٰلَ","s":4,"a":161},{"t":"ٱلنَّاسِ","s":4,"a":161}]},{"n":12,"words":[{"t":"بِٱلْبَـٰطِلِ","s":4,"a":161},{"t":"ۚ","s":4,"a":161},{"t":"وَأَعْتَدْنَا","s":4,"a":161},{"t":"لِلْكَـٰفِرِينَ","s":4,"a":161},{"t":"مِنْهُمْ","s":4,"a":161},{"t":"عَذَابًا","s":4,"a":161},{"t":"أَلِيمًۭا","s":4,"a":161},{"t":"لَّـٰكِنِ","s":4,"a":162}]},{"n":13,"words":[{"t":"ٱلرَّٰسِخُونَ","s":4,"a":162},{"t":"فِى","s":4,"a":162},{"t":"ٱلْعِلْمِ","s":4,"a":162},{"t":"مِنْهُمْ","s":4,"a":162},{"t":"وَٱلْمُؤْمِنُونَ","s":4,"a":162},{"t":"يُؤْمِنُونَ","s":4,"a":162},{"t":"بِمَآ","s":4,"a":162},{"t":"أُنزِلَ","s":4,"a":162},{"t":"إِلَيْكَ","s":4,"a":162},{"t":"وَمَآ","s":4,"a":162}]},{"n":14,"words":[{"t":"أُنزِلَ","s":4,"a":162},{"t":"مِن","s":4,"a":162},{"t":"قَبْلِكَ","s":4,"a":162},{"t":"ۚ","s":4,"a":162},{"t":"وَٱلْمُقِيمِينَ","s":4,"a":162},{"t":"ٱلصَّلَوٰةَ","s":4,"a":162},{"t":"ۚ","s":4,"a":162},{"t":"وَٱلْمُؤْتُونَ","s":4,"a":162},{"t":"ٱلزَّكَوٰةَ","s":4,"a":162}]},{"n":15,"words":[{"t":"وَٱلْمُؤْمِنُونَ","s":4,"a":162},{"t":"بِٱللَّهِ","s":4,"a":162},{"t":"وَٱلْيَوْمِ","s":4,"a":162},{"t":"ٱلْـَٔاخِرِ","s":4,"a":162},{"t":"أُو۟لَـٰٓئِكَ","s":4,"a":162},{"t":"سَنُؤْتِيهِمْ","s":4,"a":162},{"t":"أَجْرًا","s":4,"a":162},{"t":"عَظِيمًا","s":4,"a":162}]}]}