{"page":112,"juz":6,"lines":[{"n":1,"words":[{"t":"قَالُوا۟","s":5,"a":24},{"t":"يَـٰمُوسَىٰٓ","s":5,"a":24},{"t":"إِنَّا","s":5,"a":24},{"t":"لَن","s":5,"a":24},{"t":"نَّدْخُلَهَآ","s":5,"a":24},{"t":"أَبَدًۭا","s":5,"a":24},{"t":"مَّا","s":5,"a":24},{"t":"دَامُوا۟","s":5,"a":24},{"t":"فِيهَا","s":5,"a":24},{"t":"ۖ","s":5,"a":24},{"t":"فَٱذْهَبْ","s":5,"a":24}]},{"n":2,"words":[{"t":"أَنتَ","s":5,"a":24},{"t":"وَرَبُّكَ","s":5,"a":24},{"t":"فَقَـٰتِلَآ","s":5,"a":24},{"t":"إِنَّا","s":5,"a":24},{"t":"هَـٰهُنَا","s":5,"a":24},{"t":"قَـٰعِدُونَ","s":5,"a":24},{"t":"قَالَ","s":5,"a":25},{"t":"رَبِّ","s":5,"a":25}]},{"n":3,"words":[{"t":"إِنِّى","s":5,"a":25},{"t":"لَآ","s":5,"a":25},{"t":"أَمْلِكُ","s":5,"a":25},{"t":"إِلَّا","s":5,"a":25},{"t":"نَفْسِى","s":5,"a":25},{"t":"وَأَخِى","s":5,"a":25},{"t":"ۖ","s":5,"a":25},{"t":"فَٱفْرُقْ","s":5,"a":25},{"t":"بَيْنَنَا","s":5,"a":25},{"t":"وَبَيْنَ","s":5,"a":25},{"t":"ٱلْقَوْمِ","s":5,"a":25}]},{"n":4,"words":[{"t":"ٱلْفَـٰسِقِينَ","s":5,"a":25},{"t":"قَالَ","s":5,"a":26},{"t":"فَإِنَّهَا","s":5,"a":26},{"t":"مُحَرَّمَةٌ","s":5,"a":26},{"t":"عَلَيْهِمْ","s":5,"a":26},{"t":"ۛ","s":5,"a":26},{"t":"أَرْبَعِينَ","s":5,"a":26},{"t":"سَنَةًۭ","s":5,"a":26},{"t":"ۛ","s":5,"a":26}]},{"n":5,"words":[{"t":"يَتِيهُونَ","s":5,"a":26},{"t":"فِى","s":5,"a":26},{"t":"ٱلْأَرْضِ","s":5,"a":26},{"t":"ۚ","s":5,"a":26},{"t":"فَلَا","s":5,"a":26},{"t":"تَأْسَ","s":5,"a":26},{"t":"عَلَى","s":5,"a":26},{"t":"ٱلْقَوْمِ","s":5,"a":26},{"t":"ٱلْفَـٰسِقِينَ","s":5,"a":26}]},{"n":6,"words":[{"t":"۞","s":5,"a":27},{"t":"وَٱتْلُ","s":5,"a":27},{"t":"عَلَيْهِمْ","s":5,"a":27},{"t":"نَبَأَ","s":5,"a":27},{"t":"ٱبْنَىْ","s":5,"a":27},{"t":"ءَادَمَ","s":5,"a":27},{"t":"بِٱلْحَقِّ","s":5,"a":27},{"t":"إِذْ","s":5,"a":27},{"t":"قَرَّبَا","s":5,"a":27},{"t":"قُرْبَانًۭا","s":5,"a":27}]},{"n":7,"words":[{"t":"فَتُقُبِّلَ","s":5,"a":27},{"t":"مِنْ","s":5,"a":27},{"t":"أَحَدِهِمَا","s":5,"a":27},{"t":"وَلَمْ","s":5,"a":27},{"t":"يُتَقَبَّلْ","s":5,"a":27},{"t":"مِنَ","s":5,"a":27},{"t":"ٱلْـَٔاخَرِ","s":5,"a":27},{"t":"قَالَ","s":5,"a":27},{"t":"لَأَقْتُلَنَّكَ","s":5,"a":27},{"t":"ۖ","s":5,"a":27}]},{"n":8,"words":[{"t":"قَالَ","s":5,"a":27},{"t":"إِنَّمَا","s":5,"a":27},{"t":"يَتَقَبَّلُ","s":5,"a":27},{"t":"ٱللَّهُ","s":5,"a":27},{"t":"مِنَ","s":5,"a":27},{"t":"ٱلْمُتَّقِينَ","s":5,"a":27},{"t":"لَئِنۢ","s":5,"a":28},{"t":"بَسَطتَ","s":5,"a":28},{"t":"إِلَىَّ","s":5,"a":28},{"t":"يَدَكَ","s":5,"a":28}]},{"n":9,"words":[{"t":"لِتَقْتُلَنِى","s":5,"a":28},{"t":"مَآ","s":5,"a":28},{"t":"أَنَا۠","s":5,"a":28},{"t":"بِبَاسِطٍۢ","s":5,"a":28},{"t":"يَدِىَ","s":5,"a":28},{"t":"إِلَيْكَ","s":5,"a":28},{"t":"لِأَقْتُلَكَ","s":5,"a":28},{"t":"ۖ","s":5,"a":28},{"t":"إِنِّىٓ","s":5,"a":28},{"t":"أَخَافُ","s":5,"a":28},{"t":"ٱللَّهَ","s":5,"a":28}]},{"n":10,"words":[{"t":"رَبَّ","s":5,"a":28},{"t":"ٱلْعَـٰلَمِينَ","s":5,"a":28},{"t":"إِنِّىٓ","s":5,"a":29},{"t":"أُرِيدُ","s":5,"a":29},{"t":"أَن","s":5,"a":29},{"t":"تَبُوٓأَ","s":5,"a":29},{"t":"بِإِثْمِى","s":5,"a":29},{"t":"وَإِثْمِكَ","s":5,"a":29},{"t":"فَتَكُونَ","s":5,"a":29}]},{"n":11,"words":[{"t":"مِنْ","s":5,"a":29},{"t":"أَصْحَـٰبِ","s":5,"a":29},{"t":"ٱلنَّارِ","s":5,"a":29},{"t":"ۚ","s":5,"a":29},{"t":"وَذَٰلِكَ","s":5,"a":29},{"t":"جَزَٰٓؤُا۟","s":5,"a":29},{"t":"ٱلظَّـٰلِمِينَ","s":5,"a":29},{"t":"فَطَوَّعَتْ","s":5,"a":30}]},{"n":12,"words":[{"t":"لَهُۥ","s":5,"a":30},{"t":"نَفْسُهُۥ","s":5,"a":30},{"t":"قَتْلَ","s":5,"a":30},{"t":"أَخِيهِ","s":5,"a":30},{"t":"فَقَتَلَهُۥ","s":5,"a":30},{"t":"فَأَصْبَحَ","s":5,"a":30},{"t":"مِنَ","s":5,"a":30},{"t":"ٱلْخَـٰسِرِينَ","s":5,"a":30}]},{"n":13,"words":[{"t":"فَبَعَثَ","s":5,"a":31},{"t":"ٱللَّهُ","s":5,"a":31},{"t":"غُرَابًۭا","s":5,"a":31},{"t":"يَبْحَثُ","s":5,"a":31},{"t":"فِى","s":5,"a":31},{"t":"ٱلْأَرْضِ","s":5,"a":31},{"t":"لِيُرِيَهُۥ","s":5,"a":31},{"t":"كَيْفَ","s":5,"a":31},{"t":"يُوَٰرِى","s":5,"a":31}]},{"n":14,"words":[{"t":"سَوْءَةَ","s":5,"a":31},{"t":"أَخِيهِ","s":5,"a":31},{"t":"ۚ","s":5,"a":31},{"t":"قَالَ","s":5,"a":31},{"t":"يَـٰوَيْلَتَىٰٓ","s":5,"a":31},{"t":"أَعَجَزْتُ","s":5,"a":31},{"t":"أَنْ","s":5,"a":31},{"t":"أَكُونَ","s":5,"a":31},{"t":"مِثْلَ","s":5,"a":31},{"t":"هَـٰذَا","s":5,"a":31}]},{"n":15,"words":[{"t":"ٱلْغُرَابِ","s":5,"a":31},{"t":"فَأُوَٰرِىَ","s":5,"a":31},{"t":"سَوْءَةَ","s":5,"a":31},{"t":"أَخِى","s":5,"a":31},{"t":"ۖ","s":5,"a":31},{"t":"فَأَصْبَحَ","s":5,"a":31},{"t":"مِنَ","s":5,"a":31},{"t":"ٱلنَّـٰدِمِينَ","s":5,"a":31}]}]}