{"page":154,"juz":8,"lines":[{"n":1,"words":[{"t":"۞","s":7,"a":31},{"t":"يَـٰبَنِىٓ","s":7,"a":31},{"t":"ءَادَمَ","s":7,"a":31},{"t":"خُذُوا۟","s":7,"a":31},{"t":"زِينَتَكُمْ","s":7,"a":31},{"t":"عِندَ","s":7,"a":31},{"t":"كُلِّ","s":7,"a":31},{"t":"مَسْجِدٍۢ","s":7,"a":31},{"t":"وَكُلُوا۟","s":7,"a":31},{"t":"وَٱشْرَبُوا۟","s":7,"a":31}]},{"n":2,"words":[{"t":"وَلَا","s":7,"a":31},{"t":"تُسْرِفُوٓا۟","s":7,"a":31},{"t":"ۚ","s":7,"a":31},{"t":"إِنَّهُۥ","s":7,"a":31},{"t":"لَا","s":7,"a":31},{"t":"يُحِبُّ","s":7,"a":31},{"t":"ٱلْمُسْرِفِينَ","s":7,"a":31},{"t":"قُلْ","s":7,"a":32},{"t":"مَنْ","s":7,"a":32},{"t":"حَرَّمَ","s":7,"a":32},{"t":"زِينَةَ","s":7,"a":32},{"t":"ٱللَّهِ","s":7,"a":32}]},{"n":3,"words":[{"t":"ٱلَّتِىٓ","s":7,"a":32},{"t":"أَخْرَجَ","s":7,"a":32},{"t":"لِعِبَادِهِۦ","s":7,"a":32},{"t":"وَٱلطَّيِّبَـٰتِ","s":7,"a":32},{"t":"مِنَ","s":7,"a":32},{"t":"ٱلرِّزْقِ","s":7,"a":32},{"t":"ۚ","s":7,"a":32},{"t":"قُلْ","s":7,"a":32},{"t":"هِىَ","s":7,"a":32},{"t":"لِلَّذِينَ","s":7,"a":32},{"t":"ءَامَنُوا۟","s":7,"a":32}]},{"n":4,"words":[{"t":"فِى","s":7,"a":32},{"t":"ٱلْحَيَوٰةِ","s":7,"a":32},{"t":"ٱلدُّنْيَا","s":7,"a":32},{"t":"خَالِصَةًۭ","s":7,"a":32},{"t":"يَوْمَ","s":7,"a":32},{"t":"ٱلْقِيَـٰمَةِ","s":7,"a":32},{"t":"ۗ","s":7,"a":32},{"t":"كَذَٰلِكَ","s":7,"a":32},{"t":"نُفَصِّلُ","s":7,"a":32},{"t":"ٱلْـَٔايَـٰتِ","s":7,"a":32}]},{"n":5,"words":[{"t":"لِقَوْمٍۢ","s":7,"a":32},{"t":"يَعْلَمُونَ","s":7,"a":32},{"t":"قُلْ","s":7,"a":33},{"t":"إِنَّمَا","s":7,"a":33},{"t":"حَرَّمَ","s":7,"a":33},{"t":"رَبِّىَ","s":7,"a":33},{"t":"ٱلْفَوَٰحِشَ","s":7,"a":33},{"t":"مَا","s":7,"a":33},{"t":"ظَهَرَ","s":7,"a":33},{"t":"مِنْهَا","s":7,"a":33},{"t":"وَمَا","s":7,"a":33}]},{"n":6,"words":[{"t":"بَطَنَ","s":7,"a":33},{"t":"وَٱلْإِثْمَ","s":7,"a":33},{"t":"وَٱلْبَغْىَ","s":7,"a":33},{"t":"بِغَيْرِ","s":7,"a":33},{"t":"ٱلْحَقِّ","s":7,"a":33},{"t":"وَأَن","s":7,"a":33},{"t":"تُشْرِكُوا۟","s":7,"a":33},{"t":"بِٱللَّهِ","s":7,"a":33},{"t":"مَا","s":7,"a":33},{"t":"لَمْ","s":7,"a":33},{"t":"يُنَزِّلْ","s":7,"a":33},{"t":"بِهِۦ","s":7,"a":33}]},{"n":7,"words":[{"t":"سُلْطَـٰنًۭا","s":7,"a":33},{"t":"وَأَن","s":7,"a":33},{"t":"تَقُولُوا۟","s":7,"a":33},{"t":"عَلَى","s":7,"a":33},{"t":"ٱللَّهِ","s":7,"a":33},{"t":"مَا","s":7,"a":33},{"t":"لَا","s":7,"a":33},{"t":"تَعْلَمُونَ","s":7,"a":33},{"t":"وَلِكُلِّ","s":7,"a":34},{"t":"أُمَّةٍ","s":7,"a":34},{"t":"أَجَلٌۭ","s":7,"a":34},{"t":"ۖ","s":7,"a":34}]},{"n":8,"words":[{"t":"فَإِذَا","s":7,"a":34},{"t":"جَآءَ","s":7,"a":34},{"t":"أَجَلُهُمْ","s":7,"a":34},{"t":"لَا","s":7,"a":34},{"t":"يَسْتَأْخِرُونَ","s":7,"a":34},{"t":"سَاعَةًۭ","s":7,"a":34},{"t":"ۖ","s":7,"a":34},{"t":"وَلَا","s":7,"a":34},{"t":"يَسْتَقْدِمُونَ","s":7,"a":34}]},{"n":9,"words":[{"t":"يَـٰبَنِىٓ","s":7,"a":35},{"t":"ءَادَمَ","s":7,"a":35},{"t":"إِمَّا","s":7,"a":35},{"t":"يَأْتِيَنَّكُمْ","s":7,"a":35},{"t":"رُسُلٌۭ","s":7,"a":35},{"t":"مِّنكُمْ","s":7,"a":35},{"t":"يَقُصُّونَ","s":7,"a":35},{"t":"عَلَيْكُمْ","s":7,"a":35},{"t":"ءَايَـٰتِى","s":7,"a":35},{"t":"ۙ","s":7,"a":35},{"t":"فَمَنِ","s":7,"a":35}]},{"n":10,"words":[{"t":"ٱتَّقَىٰ","s":7,"a":35},{"t":"وَأَصْلَحَ","s":7,"a":35},{"t":"فَلَا","s":7,"a":35},{"t":"خَوْفٌ","s":7,"a":35},{"t":"عَلَيْهِمْ","s":7,"a":35},{"t":"وَلَا","s":7,"a":35},{"t":"هُمْ","s":7,"a":35},{"t":"يَحْزَنُونَ","s":7,"a":35},{"t":"وَٱلَّذِينَ","s":7,"a":36}]},{"n":11,"words":[{"t":"كَذَّبُوا۟","s":7,"a":36},{"t":"بِـَٔايَـٰتِنَا","s":7,"a":36},{"t":"وَٱسْتَكْبَرُوا۟","s":7,"a":36},{"t":"عَنْهَآ","s":7,"a":36},{"t":"أُو۟لَـٰٓئِكَ","s":7,"a":36},{"t":"أَصْحَـٰبُ","s":7,"a":36},{"t":"ٱلنَّارِ","s":7,"a":36},{"t":"ۖ","s":7,"a":36},{"t":"هُمْ","s":7,"a":36}]},{"n":12,"words":[{"t":"فِيهَا","s":7,"a":36},{"t":"خَـٰلِدُونَ","s":7,"a":36},{"t":"فَمَنْ","s":7,"a":37},{"t":"أَظْلَمُ","s":7,"a":37},{"t":"مِمَّنِ","s":7,"a":37},{"t":"ٱفْتَرَىٰ","s":7,"a":37},{"t":"عَلَى","s":7,"a":37},{"t":"ٱللَّهِ","s":7,"a":37},{"t":"كَذِبًا","s":7,"a":37},{"t":"أَوْ","s":7,"a":37},{"t":"كَذَّبَ","s":7,"a":37}]},{"n":13,"words":[{"t":"بِـَٔايَـٰتِهِۦٓ","s":7,"a":37},{"t":"ۚ","s":7,"a":37},{"t":"أُو۟لَـٰٓئِكَ","s":7,"a":37},{"t":"يَنَالُهُمْ","s":7,"a":37},{"t":"نَصِيبُهُم","s":7,"a":37},{"t":"مِّنَ","s":7,"a":37},{"t":"ٱلْكِتَـٰبِ","s":7,"a":37},{"t":"ۖ","s":7,"a":37},{"t":"حَتَّىٰٓ","s":7,"a":37},{"t":"إِذَا","s":7,"a":37},{"t":"جَآءَتْهُمْ","s":7,"a":37}]},{"n":14,"words":[{"t":"رُسُلُنَا","s":7,"a":37},{"t":"يَتَوَفَّوْنَهُمْ","s":7,"a":37},{"t":"قَالُوٓا۟","s":7,"a":37},{"t":"أَيْنَ","s":7,"a":37},{"t":"مَا","s":7,"a":37},{"t":"كُنتُمْ","s":7,"a":37},{"t":"تَدْعُونَ","s":7,"a":37},{"t":"مِن","s":7,"a":37},{"t":"دُونِ","s":7,"a":37},{"t":"ٱللَّهِ","s":7,"a":37},{"t":"ۖ","s":7,"a":37}]},{"n":15,"words":[{"t":"قَالُوا۟","s":7,"a":37},{"t":"ضَلُّوا۟","s":7,"a":37},{"t":"عَنَّا","s":7,"a":37},{"t":"وَشَهِدُوا۟","s":7,"a":37},{"t":"عَلَىٰٓ","s":7,"a":37},{"t":"أَنفُسِهِمْ","s":7,"a":37},{"t":"أَنَّهُمْ","s":7,"a":37},{"t":"كَانُوا۟","s":7,"a":37},{"t":"كَـٰفِرِينَ","s":7,"a":37}]}]}