{"page":219,"juz":11,"lines":[{"n":1,"words":[{"t":"قَالَ","s":10,"a":89},{"t":"قَدْ","s":10,"a":89},{"t":"أُجِيبَت","s":10,"a":89},{"t":"دَّعْوَتُكُمَا","s":10,"a":89},{"t":"فَٱسْتَقِيمَا","s":10,"a":89},{"t":"وَلَا","s":10,"a":89},{"t":"تَتَّبِعَآنِّ","s":10,"a":89},{"t":"سَبِيلَ","s":10,"a":89}]},{"n":2,"words":[{"t":"ٱلَّذِينَ","s":10,"a":89},{"t":"لَا","s":10,"a":89},{"t":"يَعْلَمُونَ","s":10,"a":89},{"t":"۞","s":10,"a":90},{"t":"وَجَـٰوَزْنَا","s":10,"a":90},{"t":"بِبَنِىٓ","s":10,"a":90},{"t":"إِسْرَٰٓءِيلَ","s":10,"a":90},{"t":"ٱلْبَحْرَ","s":10,"a":90}]},{"n":3,"words":[{"t":"فَأَتْبَعَهُمْ","s":10,"a":90},{"t":"فِرْعَوْنُ","s":10,"a":90},{"t":"وَجُنُودُهُۥ","s":10,"a":90},{"t":"بَغْيًۭا","s":10,"a":90},{"t":"وَعَدْوًا","s":10,"a":90},{"t":"ۖ","s":10,"a":90},{"t":"حَتَّىٰٓ","s":10,"a":90},{"t":"إِذَآ","s":10,"a":90},{"t":"أَدْرَكَهُ","s":10,"a":90}]},{"n":4,"words":[{"t":"ٱلْغَرَقُ","s":10,"a":90},{"t":"قَالَ","s":10,"a":90},{"t":"ءَامَنتُ","s":10,"a":90},{"t":"أَنَّهُۥ","s":10,"a":90},{"t":"لَآ","s":10,"a":90},{"t":"إِلَـٰهَ","s":10,"a":90},{"t":"إِلَّا","s":10,"a":90},{"t":"ٱلَّذِىٓ","s":10,"a":90},{"t":"ءَامَنَتْ","s":10,"a":90},{"t":"بِهِۦ","s":10,"a":90},{"t":"بَنُوٓا۟","s":10,"a":90},{"t":"إِسْرَٰٓءِيلَ","s":10,"a":90}]},{"n":5,"words":[{"t":"وَأَنَا۠","s":10,"a":90},{"t":"مِنَ","s":10,"a":90},{"t":"ٱلْمُسْلِمِينَ","s":10,"a":90},{"t":"ءَآلْـَٔـٰنَ","s":10,"a":91},{"t":"وَقَدْ","s":10,"a":91},{"t":"عَصَيْتَ","s":10,"a":91},{"t":"قَبْلُ","s":10,"a":91},{"t":"وَكُنتَ","s":10,"a":91}]},{"n":6,"words":[{"t":"مِنَ","s":10,"a":91},{"t":"ٱلْمُفْسِدِينَ","s":10,"a":91},{"t":"فَٱلْيَوْمَ","s":10,"a":92},{"t":"نُنَجِّيكَ","s":10,"a":92},{"t":"بِبَدَنِكَ","s":10,"a":92},{"t":"لِتَكُونَ","s":10,"a":92},{"t":"لِمَنْ","s":10,"a":92}]},{"n":7,"words":[{"t":"خَلْفَكَ","s":10,"a":92},{"t":"ءَايَةًۭ","s":10,"a":92},{"t":"ۚ","s":10,"a":92},{"t":"وَإِنَّ","s":10,"a":92},{"t":"كَثِيرًۭا","s":10,"a":92},{"t":"مِّنَ","s":10,"a":92},{"t":"ٱلنَّاسِ","s":10,"a":92},{"t":"عَنْ","s":10,"a":92},{"t":"ءَايَـٰتِنَا","s":10,"a":92},{"t":"لَغَـٰفِلُونَ","s":10,"a":92}]},{"n":8,"words":[{"t":"وَلَقَدْ","s":10,"a":93},{"t":"بَوَّأْنَا","s":10,"a":93},{"t":"بَنِىٓ","s":10,"a":93},{"t":"إِسْرَٰٓءِيلَ","s":10,"a":93},{"t":"مُبَوَّأَ","s":10,"a":93},{"t":"صِدْقٍۢ","s":10,"a":93},{"t":"وَرَزَقْنَـٰهُم","s":10,"a":93},{"t":"مِّنَ","s":10,"a":93},{"t":"ٱلطَّيِّبَـٰتِ","s":10,"a":93}]},{"n":9,"words":[{"t":"فَمَا","s":10,"a":93},{"t":"ٱخْتَلَفُوا۟","s":10,"a":93},{"t":"حَتَّىٰ","s":10,"a":93},{"t":"جَآءَهُمُ","s":10,"a":93},{"t":"ٱلْعِلْمُ","s":10,"a":93},{"t":"ۚ","s":10,"a":93},{"t":"إِنَّ","s":10,"a":93},{"t":"رَبَّكَ","s":10,"a":93},{"t":"يَقْضِى","s":10,"a":93},{"t":"بَيْنَهُمْ","s":10,"a":93},{"t":"يَوْمَ","s":10,"a":93},{"t":"ٱلْقِيَـٰمَةِ","s":10,"a":93}]},{"n":10,"words":[{"t":"فِيمَا","s":10,"a":93},{"t":"كَانُوا۟","s":10,"a":93},{"t":"فِيهِ","s":10,"a":93},{"t":"يَخْتَلِفُونَ","s":10,"a":93},{"t":"فَإِن","s":10,"a":94},{"t":"كُنتَ","s":10,"a":94},{"t":"فِى","s":10,"a":94},{"t":"شَكٍّۢ","s":10,"a":94},{"t":"مِّمَّآ","s":10,"a":94},{"t":"أَنزَلْنَآ","s":10,"a":94},{"t":"إِلَيْكَ","s":10,"a":94}]},{"n":11,"words":[{"t":"فَسْـَٔلِ","s":10,"a":94},{"t":"ٱلَّذِينَ","s":10,"a":94},{"t":"يَقْرَءُونَ","s":10,"a":94},{"t":"ٱلْكِتَـٰبَ","s":10,"a":94},{"t":"مِن","s":10,"a":94},{"t":"قَبْلِكَ","s":10,"a":94},{"t":"ۚ","s":10,"a":94},{"t":"لَقَدْ","s":10,"a":94},{"t":"جَآءَكَ","s":10,"a":94}]},{"n":12,"words":[{"t":"ٱلْحَقُّ","s":10,"a":94},{"t":"مِن","s":10,"a":94},{"t":"رَّبِّكَ","s":10,"a":94},{"t":"فَلَا","s":10,"a":94},{"t":"تَكُونَنَّ","s":10,"a":94},{"t":"مِنَ","s":10,"a":94},{"t":"ٱلْمُمْتَرِينَ","s":10,"a":94},{"t":"وَلَا","s":10,"a":95},{"t":"تَكُونَنَّ","s":10,"a":95}]},{"n":13,"words":[{"t":"مِنَ","s":10,"a":95},{"t":"ٱلَّذِينَ","s":10,"a":95},{"t":"كَذَّبُوا۟","s":10,"a":95},{"t":"بِـَٔايَـٰتِ","s":10,"a":95},{"t":"ٱللَّهِ","s":10,"a":95},{"t":"فَتَكُونَ","s":10,"a":95},{"t":"مِنَ","s":10,"a":95},{"t":"ٱلْخَـٰسِرِينَ","s":10,"a":95}]},{"n":14,"words":[{"t":"إِنَّ","s":10,"a":96},{"t":"ٱلَّذِينَ","s":10,"a":96},{"t":"حَقَّتْ","s":10,"a":96},{"t":"عَلَيْهِمْ","s":10,"a":96},{"t":"كَلِمَتُ","s":10,"a":96},{"t":"رَبِّكَ","s":10,"a":96},{"t":"لَا","s":10,"a":96},{"t":"يُؤْمِنُونَ","s":10,"a":96}]},{"n":15,"words":[{"t":"وَلَوْ","s":10,"a":97},{"t":"جَآءَتْهُمْ","s":10,"a":97},{"t":"كُلُّ","s":10,"a":97},{"t":"ءَايَةٍ","s":10,"a":97},{"t":"حَتَّىٰ","s":10,"a":97},{"t":"يَرَوُا۟","s":10,"a":97},{"t":"ٱلْعَذَابَ","s":10,"a":97},{"t":"ٱلْأَلِيمَ","s":10,"a":97}]}]}