{"page":224,"juz":12,"lines":[{"n":1,"words":[{"t":"أُو۟لَـٰٓئِكَ","s":11,"a":20},{"t":"لَمْ","s":11,"a":20},{"t":"يَكُونُوا۟","s":11,"a":20},{"t":"مُعْجِزِينَ","s":11,"a":20},{"t":"فِى","s":11,"a":20},{"t":"ٱلْأَرْضِ","s":11,"a":20},{"t":"وَمَا","s":11,"a":20},{"t":"كَانَ","s":11,"a":20},{"t":"لَهُم","s":11,"a":20},{"t":"مِّن","s":11,"a":20}]},{"n":2,"words":[{"t":"دُونِ","s":11,"a":20},{"t":"ٱللَّهِ","s":11,"a":20},{"t":"مِنْ","s":11,"a":20},{"t":"أَوْلِيَآءَ","s":11,"a":20},{"t":"ۘ","s":11,"a":20},{"t":"يُضَـٰعَفُ","s":11,"a":20},{"t":"لَهُمُ","s":11,"a":20},{"t":"ٱلْعَذَابُ","s":11,"a":20},{"t":"ۚ","s":11,"a":20},{"t":"مَا","s":11,"a":20},{"t":"كَانُوا۟","s":11,"a":20},{"t":"يَسْتَطِيعُونَ","s":11,"a":20}]},{"n":3,"words":[{"t":"ٱلسَّمْعَ","s":11,"a":20},{"t":"وَمَا","s":11,"a":20},{"t":"كَانُوا۟","s":11,"a":20},{"t":"يُبْصِرُونَ","s":11,"a":20},{"t":"أُو۟لَـٰٓئِكَ","s":11,"a":21},{"t":"ٱلَّذِينَ","s":11,"a":21},{"t":"خَسِرُوٓا۟","s":11,"a":21}]},{"n":4,"words":[{"t":"أَنفُسَهُمْ","s":11,"a":21},{"t":"وَضَلَّ","s":11,"a":21},{"t":"عَنْهُم","s":11,"a":21},{"t":"مَّا","s":11,"a":21},{"t":"كَانُوا۟","s":11,"a":21},{"t":"يَفْتَرُونَ","s":11,"a":21},{"t":"لَا","s":11,"a":22},{"t":"جَرَمَ","s":11,"a":22},{"t":"أَنَّهُمْ","s":11,"a":22}]},{"n":5,"words":[{"t":"فِى","s":11,"a":22},{"t":"ٱلْـَٔاخِرَةِ","s":11,"a":22},{"t":"هُمُ","s":11,"a":22},{"t":"ٱلْأَخْسَرُونَ","s":11,"a":22},{"t":"إِنَّ","s":11,"a":23},{"t":"ٱلَّذِينَ","s":11,"a":23},{"t":"ءَامَنُوا۟","s":11,"a":23},{"t":"وَعَمِلُوا۟","s":11,"a":23}]},{"n":6,"words":[{"t":"ٱلصَّـٰلِحَـٰتِ","s":11,"a":23},{"t":"وَأَخْبَتُوٓا۟","s":11,"a":23},{"t":"إِلَىٰ","s":11,"a":23},{"t":"رَبِّهِمْ","s":11,"a":23},{"t":"أُو۟لَـٰٓئِكَ","s":11,"a":23},{"t":"أَصْحَـٰبُ","s":11,"a":23},{"t":"ٱلْجَنَّةِ","s":11,"a":23},{"t":"ۖ","s":11,"a":23}]},{"n":7,"words":[{"t":"هُمْ","s":11,"a":23},{"t":"فِيهَا","s":11,"a":23},{"t":"خَـٰلِدُونَ","s":11,"a":23},{"t":"۞","s":11,"a":24},{"t":"مَثَلُ","s":11,"a":24},{"t":"ٱلْفَرِيقَيْنِ","s":11,"a":24},{"t":"كَٱلْأَعْمَىٰ","s":11,"a":24}]},{"n":8,"words":[{"t":"وَٱلْأَصَمِّ","s":11,"a":24},{"t":"وَٱلْبَصِيرِ","s":11,"a":24},{"t":"وَٱلسَّمِيعِ","s":11,"a":24},{"t":"ۚ","s":11,"a":24},{"t":"هَلْ","s":11,"a":24},{"t":"يَسْتَوِيَانِ","s":11,"a":24},{"t":"مَثَلًا","s":11,"a":24},{"t":"ۚ","s":11,"a":24},{"t":"أَفَلَا","s":11,"a":24},{"t":"تَذَكَّرُونَ","s":11,"a":24}]},{"n":9,"words":[{"t":"وَلَقَدْ","s":11,"a":25},{"t":"أَرْسَلْنَا","s":11,"a":25},{"t":"نُوحًا","s":11,"a":25},{"t":"إِلَىٰ","s":11,"a":25},{"t":"قَوْمِهِۦٓ","s":11,"a":25},{"t":"إِنِّى","s":11,"a":25},{"t":"لَكُمْ","s":11,"a":25},{"t":"نَذِيرٌۭ","s":11,"a":25},{"t":"مُّبِينٌ","s":11,"a":25}]},{"n":10,"words":[{"t":"أَن","s":11,"a":26},{"t":"لَّا","s":11,"a":26},{"t":"تَعْبُدُوٓا۟","s":11,"a":26},{"t":"إِلَّا","s":11,"a":26},{"t":"ٱللَّهَ","s":11,"a":26},{"t":"ۖ","s":11,"a":26},{"t":"إِنِّىٓ","s":11,"a":26},{"t":"أَخَافُ","s":11,"a":26},{"t":"عَلَيْكُمْ","s":11,"a":26},{"t":"عَذَابَ","s":11,"a":26},{"t":"يَوْمٍ","s":11,"a":26},{"t":"أَلِيمٍۢ","s":11,"a":26}]},{"n":11,"words":[{"t":"فَقَالَ","s":11,"a":27},{"t":"ٱلْمَلَأُ","s":11,"a":27},{"t":"ٱلَّذِينَ","s":11,"a":27},{"t":"كَفَرُوا۟","s":11,"a":27},{"t":"مِن","s":11,"a":27},{"t":"قَوْمِهِۦ","s":11,"a":27},{"t":"مَا","s":11,"a":27},{"t":"نَرَىٰكَ","s":11,"a":27},{"t":"إِلَّا","s":11,"a":27},{"t":"بَشَرًۭا","s":11,"a":27}]},{"n":12,"words":[{"t":"مِّثْلَنَا","s":11,"a":27},{"t":"وَمَا","s":11,"a":27},{"t":"نَرَىٰكَ","s":11,"a":27},{"t":"ٱتَّبَعَكَ","s":11,"a":27},{"t":"إِلَّا","s":11,"a":27},{"t":"ٱلَّذِينَ","s":11,"a":27},{"t":"هُمْ","s":11,"a":27},{"t":"أَرَاذِلُنَا","s":11,"a":27},{"t":"بَادِىَ","s":11,"a":27}]},{"n":13,"words":[{"t":"ٱلرَّأْىِ","s":11,"a":27},{"t":"وَمَا","s":11,"a":27},{"t":"نَرَىٰ","s":11,"a":27},{"t":"لَكُمْ","s":11,"a":27},{"t":"عَلَيْنَا","s":11,"a":27},{"t":"مِن","s":11,"a":27},{"t":"فَضْلٍۭ","s":11,"a":27},{"t":"بَلْ","s":11,"a":27},{"t":"نَظُنُّكُمْ","s":11,"a":27},{"t":"كَـٰذِبِينَ","s":11,"a":27}]},{"n":14,"words":[{"t":"قَالَ","s":11,"a":28},{"t":"يَـٰقَوْمِ","s":11,"a":28},{"t":"أَرَءَيْتُمْ","s":11,"a":28},{"t":"إِن","s":11,"a":28},{"t":"كُنتُ","s":11,"a":28},{"t":"عَلَىٰ","s":11,"a":28},{"t":"بَيِّنَةٍۢ","s":11,"a":28},{"t":"مِّن","s":11,"a":28},{"t":"رَّبِّى","s":11,"a":28},{"t":"وَءَاتَىٰنِى","s":11,"a":28},{"t":"رَحْمَةًۭ","s":11,"a":28}]},{"n":15,"words":[{"t":"مِّنْ","s":11,"a":28},{"t":"عِندِهِۦ","s":11,"a":28},{"t":"فَعُمِّيَتْ","s":11,"a":28},{"t":"عَلَيْكُمْ","s":11,"a":28},{"t":"أَنُلْزِمُكُمُوهَا","s":11,"a":28},{"t":"وَأَنتُمْ","s":11,"a":28},{"t":"لَهَا","s":11,"a":28},{"t":"كَـٰرِهُونَ","s":11,"a":28}]}]}