{"page":228,"juz":12,"lines":[{"n":1,"words":[{"t":"إِن","s":11,"a":54},{"t":"نَّقُولُ","s":11,"a":54},{"t":"إِلَّا","s":11,"a":54},{"t":"ٱعْتَرَىٰكَ","s":11,"a":54},{"t":"بَعْضُ","s":11,"a":54},{"t":"ءَالِهَتِنَا","s":11,"a":54},{"t":"بِسُوٓءٍۢ","s":11,"a":54},{"t":"ۗ","s":11,"a":54},{"t":"قَالَ","s":11,"a":54},{"t":"إِنِّىٓ","s":11,"a":54},{"t":"أُشْهِدُ","s":11,"a":54},{"t":"ٱللَّهَ","s":11,"a":54}]},{"n":2,"words":[{"t":"وَٱشْهَدُوٓا۟","s":11,"a":54},{"t":"أَنِّى","s":11,"a":54},{"t":"بَرِىٓءٌۭ","s":11,"a":54},{"t":"مِّمَّا","s":11,"a":54},{"t":"تُشْرِكُونَ","s":11,"a":54},{"t":"مِن","s":11,"a":55},{"t":"دُونِهِۦ","s":11,"a":55},{"t":"ۖ","s":11,"a":55},{"t":"فَكِيدُونِى","s":11,"a":55}]},{"n":3,"words":[{"t":"جَمِيعًۭا","s":11,"a":55},{"t":"ثُمَّ","s":11,"a":55},{"t":"لَا","s":11,"a":55},{"t":"تُنظِرُونِ","s":11,"a":55},{"t":"إِنِّى","s":11,"a":56},{"t":"تَوَكَّلْتُ","s":11,"a":56},{"t":"عَلَى","s":11,"a":56},{"t":"ٱللَّهِ","s":11,"a":56},{"t":"رَبِّى","s":11,"a":56},{"t":"وَرَبِّكُم","s":11,"a":56},{"t":"ۚ","s":11,"a":56},{"t":"مَّا","s":11,"a":56}]},{"n":4,"words":[{"t":"مِن","s":11,"a":56},{"t":"دَآبَّةٍ","s":11,"a":56},{"t":"إِلَّا","s":11,"a":56},{"t":"هُوَ","s":11,"a":56},{"t":"ءَاخِذٌۢ","s":11,"a":56},{"t":"بِنَاصِيَتِهَآ","s":11,"a":56},{"t":"ۚ","s":11,"a":56},{"t":"إِنَّ","s":11,"a":56},{"t":"رَبِّى","s":11,"a":56},{"t":"عَلَىٰ","s":11,"a":56},{"t":"صِرَٰطٍۢ","s":11,"a":56},{"t":"مُّسْتَقِيمٍۢ","s":11,"a":56}]},{"n":5,"words":[{"t":"فَإِن","s":11,"a":57},{"t":"تَوَلَّوْا۟","s":11,"a":57},{"t":"فَقَدْ","s":11,"a":57},{"t":"أَبْلَغْتُكُم","s":11,"a":57},{"t":"مَّآ","s":11,"a":57},{"t":"أُرْسِلْتُ","s":11,"a":57},{"t":"بِهِۦٓ","s":11,"a":57},{"t":"إِلَيْكُمْ","s":11,"a":57},{"t":"ۚ","s":11,"a":57},{"t":"وَيَسْتَخْلِفُ","s":11,"a":57}]},{"n":6,"words":[{"t":"رَبِّى","s":11,"a":57},{"t":"قَوْمًا","s":11,"a":57},{"t":"غَيْرَكُمْ","s":11,"a":57},{"t":"وَلَا","s":11,"a":57},{"t":"تَضُرُّونَهُۥ","s":11,"a":57},{"t":"شَيْـًٔا","s":11,"a":57},{"t":"ۚ","s":11,"a":57},{"t":"إِنَّ","s":11,"a":57},{"t":"رَبِّى","s":11,"a":57},{"t":"عَلَىٰ","s":11,"a":57},{"t":"كُلِّ","s":11,"a":57},{"t":"شَىْءٍ","s":11,"a":57},{"t":"حَفِيظٌۭ","s":11,"a":57}]},{"n":7,"words":[{"t":"وَلَمَّا","s":11,"a":58},{"t":"جَآءَ","s":11,"a":58},{"t":"أَمْرُنَا","s":11,"a":58},{"t":"نَجَّيْنَا","s":11,"a":58},{"t":"هُودًۭا","s":11,"a":58},{"t":"وَٱلَّذِينَ","s":11,"a":58},{"t":"ءَامَنُوا۟","s":11,"a":58},{"t":"مَعَهُۥ","s":11,"a":58},{"t":"بِرَحْمَةٍۢ","s":11,"a":58}]},{"n":8,"words":[{"t":"مِّنَّا","s":11,"a":58},{"t":"وَنَجَّيْنَـٰهُم","s":11,"a":58},{"t":"مِّنْ","s":11,"a":58},{"t":"عَذَابٍ","s":11,"a":58},{"t":"غَلِيظٍۢ","s":11,"a":58},{"t":"وَتِلْكَ","s":11,"a":59},{"t":"عَادٌۭ","s":11,"a":59},{"t":"ۖ","s":11,"a":59},{"t":"جَحَدُوا۟","s":11,"a":59},{"t":"بِـَٔايَـٰتِ","s":11,"a":59}]},{"n":9,"words":[{"t":"رَبِّهِمْ","s":11,"a":59},{"t":"وَعَصَوْا۟","s":11,"a":59},{"t":"رُسُلَهُۥ","s":11,"a":59},{"t":"وَٱتَّبَعُوٓا۟","s":11,"a":59},{"t":"أَمْرَ","s":11,"a":59},{"t":"كُلِّ","s":11,"a":59},{"t":"جَبَّارٍ","s":11,"a":59},{"t":"عَنِيدٍۢ","s":11,"a":59},{"t":"وَأُتْبِعُوا۟","s":11,"a":60}]},{"n":10,"words":[{"t":"فِى","s":11,"a":60},{"t":"هَـٰذِهِ","s":11,"a":60},{"t":"ٱلدُّنْيَا","s":11,"a":60},{"t":"لَعْنَةًۭ","s":11,"a":60},{"t":"وَيَوْمَ","s":11,"a":60},{"t":"ٱلْقِيَـٰمَةِ","s":11,"a":60},{"t":"ۗ","s":11,"a":60},{"t":"أَلَآ","s":11,"a":60},{"t":"إِنَّ","s":11,"a":60},{"t":"عَادًۭا","s":11,"a":60},{"t":"كَفَرُوا۟","s":11,"a":60},{"t":"رَبَّهُمْ","s":11,"a":60},{"t":"ۗ","s":11,"a":60},{"t":"أَلَا","s":11,"a":60}]},{"n":11,"words":[{"t":"بُعْدًۭا","s":11,"a":60},{"t":"لِّعَادٍۢ","s":11,"a":60},{"t":"قَوْمِ","s":11,"a":60},{"t":"هُودٍۢ","s":11,"a":60},{"t":"۞","s":11,"a":61},{"t":"وَإِلَىٰ","s":11,"a":61},{"t":"ثَمُودَ","s":11,"a":61},{"t":"أَخَاهُمْ","s":11,"a":61},{"t":"صَـٰلِحًۭا","s":11,"a":61},{"t":"ۚ","s":11,"a":61},{"t":"قَالَ","s":11,"a":61}]},{"n":12,"words":[{"t":"يَـٰقَوْمِ","s":11,"a":61},{"t":"ٱعْبُدُوا۟","s":11,"a":61},{"t":"ٱللَّهَ","s":11,"a":61},{"t":"مَا","s":11,"a":61},{"t":"لَكُم","s":11,"a":61},{"t":"مِّنْ","s":11,"a":61},{"t":"إِلَـٰهٍ","s":11,"a":61},{"t":"غَيْرُهُۥ","s":11,"a":61},{"t":"ۖ","s":11,"a":61},{"t":"هُوَ","s":11,"a":61},{"t":"أَنشَأَكُم","s":11,"a":61},{"t":"مِّنَ","s":11,"a":61},{"t":"ٱلْأَرْضِ","s":11,"a":61}]},{"n":13,"words":[{"t":"وَٱسْتَعْمَرَكُمْ","s":11,"a":61},{"t":"فِيهَا","s":11,"a":61},{"t":"فَٱسْتَغْفِرُوهُ","s":11,"a":61},{"t":"ثُمَّ","s":11,"a":61},{"t":"تُوبُوٓا۟","s":11,"a":61},{"t":"إِلَيْهِ","s":11,"a":61},{"t":"ۚ","s":11,"a":61},{"t":"إِنَّ","s":11,"a":61},{"t":"رَبِّى","s":11,"a":61},{"t":"قَرِيبٌۭ","s":11,"a":61},{"t":"مُّجِيبٌۭ","s":11,"a":61}]},{"n":14,"words":[{"t":"قَالُوا۟","s":11,"a":62},{"t":"يَـٰصَـٰلِحُ","s":11,"a":62},{"t":"قَدْ","s":11,"a":62},{"t":"كُنتَ","s":11,"a":62},{"t":"فِينَا","s":11,"a":62},{"t":"مَرْجُوًّۭا","s":11,"a":62},{"t":"قَبْلَ","s":11,"a":62},{"t":"هَـٰذَآ","s":11,"a":62},{"t":"ۖ","s":11,"a":62},{"t":"أَتَنْهَىٰنَآ","s":11,"a":62},{"t":"أَن","s":11,"a":62}]},{"n":15,"words":[{"t":"نَّعْبُدَ","s":11,"a":62},{"t":"مَا","s":11,"a":62},{"t":"يَعْبُدُ","s":11,"a":62},{"t":"ءَابَآؤُنَا","s":11,"a":62},{"t":"وَإِنَّنَا","s":11,"a":62},{"t":"لَفِى","s":11,"a":62},{"t":"شَكٍّۢ","s":11,"a":62},{"t":"مِّمَّا","s":11,"a":62},{"t":"تَدْعُونَآ","s":11,"a":62},{"t":"إِلَيْهِ","s":11,"a":62},{"t":"مُرِيبٍۢ","s":11,"a":62}]}]}