{"page":302,"juz":16,"lines":[{"n":1,"words":[{"t":"۞","s":18,"a":75},{"t":"قَالَ","s":18,"a":75},{"t":"أَلَمْ","s":18,"a":75},{"t":"أَقُل","s":18,"a":75},{"t":"لَّكَ","s":18,"a":75},{"t":"إِنَّكَ","s":18,"a":75},{"t":"لَن","s":18,"a":75},{"t":"تَسْتَطِيعَ","s":18,"a":75},{"t":"مَعِىَ","s":18,"a":75},{"t":"صَبْرًۭا","s":18,"a":75},{"t":"قَالَ","s":18,"a":76},{"t":"إِن","s":18,"a":76}]},{"n":2,"words":[{"t":"سَأَلْتُكَ","s":18,"a":76},{"t":"عَن","s":18,"a":76},{"t":"شَىْءٍۭ","s":18,"a":76},{"t":"بَعْدَهَا","s":18,"a":76},{"t":"فَلَا","s":18,"a":76},{"t":"تُصَـٰحِبْنِى","s":18,"a":76},{"t":"ۖ","s":18,"a":76},{"t":"قَدْ","s":18,"a":76},{"t":"بَلَغْتَ","s":18,"a":76},{"t":"مِن","s":18,"a":76},{"t":"لَّدُنِّى","s":18,"a":76},{"t":"عُذْرًۭا","s":18,"a":76}]},{"n":3,"words":[{"t":"فَٱنطَلَقَا","s":18,"a":77},{"t":"حَتَّىٰٓ","s":18,"a":77},{"t":"إِذَآ","s":18,"a":77},{"t":"أَتَيَآ","s":18,"a":77},{"t":"أَهْلَ","s":18,"a":77},{"t":"قَرْيَةٍ","s":18,"a":77},{"t":"ٱسْتَطْعَمَآ","s":18,"a":77},{"t":"أَهْلَهَا","s":18,"a":77},{"t":"فَأَبَوْا۟","s":18,"a":77}]},{"n":4,"words":[{"t":"أَن","s":18,"a":77},{"t":"يُضَيِّفُوهُمَا","s":18,"a":77},{"t":"فَوَجَدَا","s":18,"a":77},{"t":"فِيهَا","s":18,"a":77},{"t":"جِدَارًۭا","s":18,"a":77},{"t":"يُرِيدُ","s":18,"a":77},{"t":"أَن","s":18,"a":77},{"t":"يَنقَضَّ","s":18,"a":77},{"t":"فَأَقَامَهُۥ","s":18,"a":77},{"t":"ۖ","s":18,"a":77}]},{"n":5,"words":[{"t":"قَالَ","s":18,"a":77},{"t":"لَوْ","s":18,"a":77},{"t":"شِئْتَ","s":18,"a":77},{"t":"لَتَّخَذْتَ","s":18,"a":77},{"t":"عَلَيْهِ","s":18,"a":77},{"t":"أَجْرًۭا","s":18,"a":77},{"t":"قَالَ","s":18,"a":78},{"t":"هَـٰذَا","s":18,"a":78},{"t":"فِرَاقُ","s":18,"a":78},{"t":"بَيْنِى","s":18,"a":78}]},{"n":6,"words":[{"t":"وَبَيْنِكَ","s":18,"a":78},{"t":"ۚ","s":18,"a":78},{"t":"سَأُنَبِّئُكَ","s":18,"a":78},{"t":"بِتَأْوِيلِ","s":18,"a":78},{"t":"مَا","s":18,"a":78},{"t":"لَمْ","s":18,"a":78},{"t":"تَسْتَطِع","s":18,"a":78},{"t":"عَّلَيْهِ","s":18,"a":78},{"t":"صَبْرًا","s":18,"a":78},{"t":"أَمَّا","s":18,"a":79}]},{"n":7,"words":[{"t":"ٱلسَّفِينَةُ","s":18,"a":79},{"t":"فَكَانَتْ","s":18,"a":79},{"t":"لِمَسَـٰكِينَ","s":18,"a":79},{"t":"يَعْمَلُونَ","s":18,"a":79},{"t":"فِى","s":18,"a":79},{"t":"ٱلْبَحْرِ","s":18,"a":79},{"t":"فَأَرَدتُّ","s":18,"a":79},{"t":"أَنْ","s":18,"a":79},{"t":"أَعِيبَهَا","s":18,"a":79}]},{"n":8,"words":[{"t":"وَكَانَ","s":18,"a":79},{"t":"وَرَآءَهُم","s":18,"a":79},{"t":"مَّلِكٌۭ","s":18,"a":79},{"t":"يَأْخُذُ","s":18,"a":79},{"t":"كُلَّ","s":18,"a":79},{"t":"سَفِينَةٍ","s":18,"a":79},{"t":"غَصْبًۭا","s":18,"a":79},{"t":"وَأَمَّا","s":18,"a":80},{"t":"ٱلْغُلَـٰمُ","s":18,"a":80}]},{"n":9,"words":[{"t":"فَكَانَ","s":18,"a":80},{"t":"أَبَوَاهُ","s":18,"a":80},{"t":"مُؤْمِنَيْنِ","s":18,"a":80},{"t":"فَخَشِينَآ","s":18,"a":80},{"t":"أَن","s":18,"a":80},{"t":"يُرْهِقَهُمَا","s":18,"a":80},{"t":"طُغْيَـٰنًۭا","s":18,"a":80},{"t":"وَكُفْرًۭا","s":18,"a":80}]},{"n":10,"words":[{"t":"فَأَرَدْنَآ","s":18,"a":81},{"t":"أَن","s":18,"a":81},{"t":"يُبْدِلَهُمَا","s":18,"a":81},{"t":"رَبُّهُمَا","s":18,"a":81},{"t":"خَيْرًۭا","s":18,"a":81},{"t":"مِّنْهُ","s":18,"a":81},{"t":"زَكَوٰةًۭ","s":18,"a":81},{"t":"وَأَقْرَبَ","s":18,"a":81},{"t":"رُحْمًۭا","s":18,"a":81}]},{"n":11,"words":[{"t":"وَأَمَّا","s":18,"a":82},{"t":"ٱلْجِدَارُ","s":18,"a":82},{"t":"فَكَانَ","s":18,"a":82},{"t":"لِغُلَـٰمَيْنِ","s":18,"a":82},{"t":"يَتِيمَيْنِ","s":18,"a":82},{"t":"فِى","s":18,"a":82},{"t":"ٱلْمَدِينَةِ","s":18,"a":82},{"t":"وَكَانَ","s":18,"a":82}]},{"n":12,"words":[{"t":"تَحْتَهُۥ","s":18,"a":82},{"t":"كَنزٌۭ","s":18,"a":82},{"t":"لَّهُمَا","s":18,"a":82},{"t":"وَكَانَ","s":18,"a":82},{"t":"أَبُوهُمَا","s":18,"a":82},{"t":"صَـٰلِحًۭا","s":18,"a":82},{"t":"فَأَرَادَ","s":18,"a":82},{"t":"رَبُّكَ","s":18,"a":82},{"t":"أَن","s":18,"a":82},{"t":"يَبْلُغَآ","s":18,"a":82}]},{"n":13,"words":[{"t":"أَشُدَّهُمَا","s":18,"a":82},{"t":"وَيَسْتَخْرِجَا","s":18,"a":82},{"t":"كَنزَهُمَا","s":18,"a":82},{"t":"رَحْمَةًۭ","s":18,"a":82},{"t":"مِّن","s":18,"a":82},{"t":"رَّبِّكَ","s":18,"a":82},{"t":"ۚ","s":18,"a":82},{"t":"وَمَا","s":18,"a":82},{"t":"فَعَلْتُهُۥ","s":18,"a":82}]},{"n":14,"words":[{"t":"عَنْ","s":18,"a":82},{"t":"أَمْرِى","s":18,"a":82},{"t":"ۚ","s":18,"a":82},{"t":"ذَٰلِكَ","s":18,"a":82},{"t":"تَأْوِيلُ","s":18,"a":82},{"t":"مَا","s":18,"a":82},{"t":"لَمْ","s":18,"a":82},{"t":"تَسْطِع","s":18,"a":82},{"t":"عَّلَيْهِ","s":18,"a":82},{"t":"صَبْرًۭا","s":18,"a":82},{"t":"وَيَسْـَٔلُونَكَ","s":18,"a":83}]},{"n":15,"words":[{"t":"عَن","s":18,"a":83},{"t":"ذِى","s":18,"a":83},{"t":"ٱلْقَرْنَيْنِ","s":18,"a":83},{"t":"ۖ","s":18,"a":83},{"t":"قُلْ","s":18,"a":83},{"t":"سَأَتْلُوا۟","s":18,"a":83},{"t":"عَلَيْكُم","s":18,"a":83},{"t":"مِّنْهُ","s":18,"a":83},{"t":"ذِكْرًا","s":18,"a":83}]}]}