{"page":328,"juz":17,"lines":[{"n":1,"words":[{"t":"وَجَعَلْنَـٰهُمْ","s":21,"a":73},{"t":"أَئِمَّةًۭ","s":21,"a":73},{"t":"يَهْدُونَ","s":21,"a":73},{"t":"بِأَمْرِنَا","s":21,"a":73},{"t":"وَأَوْحَيْنَآ","s":21,"a":73},{"t":"إِلَيْهِمْ","s":21,"a":73},{"t":"فِعْلَ","s":21,"a":73}]},{"n":2,"words":[{"t":"ٱلْخَيْرَٰتِ","s":21,"a":73},{"t":"وَإِقَامَ","s":21,"a":73},{"t":"ٱلصَّلَوٰةِ","s":21,"a":73},{"t":"وَإِيتَآءَ","s":21,"a":73},{"t":"ٱلزَّكَوٰةِ","s":21,"a":73},{"t":"ۖ","s":21,"a":73},{"t":"وَكَانُوا۟","s":21,"a":73},{"t":"لَنَا","s":21,"a":73}]},{"n":3,"words":[{"t":"عَـٰبِدِينَ","s":21,"a":73},{"t":"وَلُوطًا","s":21,"a":74},{"t":"ءَاتَيْنَـٰهُ","s":21,"a":74},{"t":"حُكْمًۭا","s":21,"a":74},{"t":"وَعِلْمًۭا","s":21,"a":74},{"t":"وَنَجَّيْنَـٰهُ","s":21,"a":74},{"t":"مِنَ","s":21,"a":74}]},{"n":4,"words":[{"t":"ٱلْقَرْيَةِ","s":21,"a":74},{"t":"ٱلَّتِى","s":21,"a":74},{"t":"كَانَت","s":21,"a":74},{"t":"تَّعْمَلُ","s":21,"a":74},{"t":"ٱلْخَبَـٰٓئِثَ","s":21,"a":74},{"t":"ۗ","s":21,"a":74},{"t":"إِنَّهُمْ","s":21,"a":74},{"t":"كَانُوا۟","s":21,"a":74},{"t":"قَوْمَ","s":21,"a":74},{"t":"سَوْءٍۢ","s":21,"a":74}]},{"n":5,"words":[{"t":"فَـٰسِقِينَ","s":21,"a":74},{"t":"وَأَدْخَلْنَـٰهُ","s":21,"a":75},{"t":"فِى","s":21,"a":75},{"t":"رَحْمَتِنَآ","s":21,"a":75},{"t":"ۖ","s":21,"a":75},{"t":"إِنَّهُۥ","s":21,"a":75},{"t":"مِنَ","s":21,"a":75},{"t":"ٱلصَّـٰلِحِينَ","s":21,"a":75}]},{"n":6,"words":[{"t":"وَنُوحًا","s":21,"a":76},{"t":"إِذْ","s":21,"a":76},{"t":"نَادَىٰ","s":21,"a":76},{"t":"مِن","s":21,"a":76},{"t":"قَبْلُ","s":21,"a":76},{"t":"فَٱسْتَجَبْنَا","s":21,"a":76},{"t":"لَهُۥ","s":21,"a":76},{"t":"فَنَجَّيْنَـٰهُ","s":21,"a":76}]},{"n":7,"words":[{"t":"وَأَهْلَهُۥ","s":21,"a":76},{"t":"مِنَ","s":21,"a":76},{"t":"ٱلْكَرْبِ","s":21,"a":76},{"t":"ٱلْعَظِيمِ","s":21,"a":76},{"t":"وَنَصَرْنَـٰهُ","s":21,"a":77},{"t":"مِنَ","s":21,"a":77},{"t":"ٱلْقَوْمِ","s":21,"a":77}]},{"n":8,"words":[{"t":"ٱلَّذِينَ","s":21,"a":77},{"t":"كَذَّبُوا۟","s":21,"a":77},{"t":"بِـَٔايَـٰتِنَآ","s":21,"a":77},{"t":"ۚ","s":21,"a":77},{"t":"إِنَّهُمْ","s":21,"a":77},{"t":"كَانُوا۟","s":21,"a":77},{"t":"قَوْمَ","s":21,"a":77},{"t":"سَوْءٍۢ","s":21,"a":77},{"t":"فَأَغْرَقْنَـٰهُمْ","s":21,"a":77}]},{"n":9,"words":[{"t":"أَجْمَعِينَ","s":21,"a":77},{"t":"وَدَاوُۥدَ","s":21,"a":78},{"t":"وَسُلَيْمَـٰنَ","s":21,"a":78},{"t":"إِذْ","s":21,"a":78},{"t":"يَحْكُمَانِ","s":21,"a":78},{"t":"فِى","s":21,"a":78},{"t":"ٱلْحَرْثِ","s":21,"a":78},{"t":"إِذْ","s":21,"a":78}]},{"n":10,"words":[{"t":"نَفَشَتْ","s":21,"a":78},{"t":"فِيهِ","s":21,"a":78},{"t":"غَنَمُ","s":21,"a":78},{"t":"ٱلْقَوْمِ","s":21,"a":78},{"t":"وَكُنَّا","s":21,"a":78},{"t":"لِحُكْمِهِمْ","s":21,"a":78},{"t":"شَـٰهِدِينَ","s":21,"a":78}]},{"n":11,"words":[{"t":"فَفَهَّمْنَـٰهَا","s":21,"a":79},{"t":"سُلَيْمَـٰنَ","s":21,"a":79},{"t":"ۚ","s":21,"a":79},{"t":"وَكُلًّا","s":21,"a":79},{"t":"ءَاتَيْنَا","s":21,"a":79},{"t":"حُكْمًۭا","s":21,"a":79},{"t":"وَعِلْمًۭا","s":21,"a":79},{"t":"ۚ","s":21,"a":79},{"t":"وَسَخَّرْنَا","s":21,"a":79}]},{"n":12,"words":[{"t":"مَعَ","s":21,"a":79},{"t":"دَاوُۥدَ","s":21,"a":79},{"t":"ٱلْجِبَالَ","s":21,"a":79},{"t":"يُسَبِّحْنَ","s":21,"a":79},{"t":"وَٱلطَّيْرَ","s":21,"a":79},{"t":"ۚ","s":21,"a":79},{"t":"وَكُنَّا","s":21,"a":79},{"t":"فَـٰعِلِينَ","s":21,"a":79}]},{"n":13,"words":[{"t":"وَعَلَّمْنَـٰهُ","s":21,"a":80},{"t":"صَنْعَةَ","s":21,"a":80},{"t":"لَبُوسٍۢ","s":21,"a":80},{"t":"لَّكُمْ","s":21,"a":80},{"t":"لِتُحْصِنَكُم","s":21,"a":80},{"t":"مِّنۢ","s":21,"a":80},{"t":"بَأْسِكُمْ","s":21,"a":80},{"t":"ۖ","s":21,"a":80}]},{"n":14,"words":[{"t":"فَهَلْ","s":21,"a":80},{"t":"أَنتُمْ","s":21,"a":80},{"t":"شَـٰكِرُونَ","s":21,"a":80},{"t":"وَلِسُلَيْمَـٰنَ","s":21,"a":81},{"t":"ٱلرِّيحَ","s":21,"a":81},{"t":"عَاصِفَةًۭ","s":21,"a":81},{"t":"تَجْرِى","s":21,"a":81},{"t":"بِأَمْرِهِۦٓ","s":21,"a":81}]},{"n":15,"words":[{"t":"إِلَى","s":21,"a":81},{"t":"ٱلْأَرْضِ","s":21,"a":81},{"t":"ٱلَّتِى","s":21,"a":81},{"t":"بَـٰرَكْنَا","s":21,"a":81},{"t":"فِيهَا","s":21,"a":81},{"t":"ۚ","s":21,"a":81},{"t":"وَكُنَّا","s":21,"a":81},{"t":"بِكُلِّ","s":21,"a":81},{"t":"شَىْءٍ","s":21,"a":81},{"t":"عَـٰلِمِينَ","s":21,"a":81}]}]}