{"page":379,"juz":19,"lines":[{"n":1,"words":[{"t":"إِنِّى","s":27,"a":23},{"t":"وَجَدتُّ","s":27,"a":23},{"t":"ٱمْرَأَةًۭ","s":27,"a":23},{"t":"تَمْلِكُهُمْ","s":27,"a":23},{"t":"وَأُوتِيَتْ","s":27,"a":23},{"t":"مِن","s":27,"a":23},{"t":"كُلِّ","s":27,"a":23},{"t":"شَىْءٍۢ","s":27,"a":23},{"t":"وَلَهَا","s":27,"a":23}]},{"n":2,"words":[{"t":"عَرْشٌ","s":27,"a":23},{"t":"عَظِيمٌۭ","s":27,"a":23},{"t":"وَجَدتُّهَا","s":27,"a":24},{"t":"وَقَوْمَهَا","s":27,"a":24},{"t":"يَسْجُدُونَ","s":27,"a":24},{"t":"لِلشَّمْسِ","s":27,"a":24},{"t":"مِن","s":27,"a":24}]},{"n":3,"words":[{"t":"دُونِ","s":27,"a":24},{"t":"ٱللَّهِ","s":27,"a":24},{"t":"وَزَيَّنَ","s":27,"a":24},{"t":"لَهُمُ","s":27,"a":24},{"t":"ٱلشَّيْطَـٰنُ","s":27,"a":24},{"t":"أَعْمَـٰلَهُمْ","s":27,"a":24},{"t":"فَصَدَّهُمْ","s":27,"a":24},{"t":"عَنِ","s":27,"a":24},{"t":"ٱلسَّبِيلِ","s":27,"a":24}]},{"n":4,"words":[{"t":"فَهُمْ","s":27,"a":24},{"t":"لَا","s":27,"a":24},{"t":"يَهْتَدُونَ","s":27,"a":24},{"t":"أَلَّا","s":27,"a":25},{"t":"يَسْجُدُوا۟","s":27,"a":25},{"t":"لِلَّهِ","s":27,"a":25},{"t":"ٱلَّذِى","s":27,"a":25},{"t":"يُخْرِجُ","s":27,"a":25},{"t":"ٱلْخَبْءَ","s":27,"a":25}]},{"n":5,"words":[{"t":"فِى","s":27,"a":25},{"t":"ٱلسَّمَـٰوَٰتِ","s":27,"a":25},{"t":"وَٱلْأَرْضِ","s":27,"a":25},{"t":"وَيَعْلَمُ","s":27,"a":25},{"t":"مَا","s":27,"a":25},{"t":"تُخْفُونَ","s":27,"a":25},{"t":"وَمَا","s":27,"a":25},{"t":"تُعْلِنُونَ","s":27,"a":25},{"t":"ٱللَّهُ","s":27,"a":26}]},{"n":6,"words":[{"t":"لَآ","s":27,"a":26},{"t":"إِلَـٰهَ","s":27,"a":26},{"t":"إِلَّا","s":27,"a":26},{"t":"هُوَ","s":27,"a":26},{"t":"رَبُّ","s":27,"a":26},{"t":"ٱلْعَرْشِ","s":27,"a":26},{"t":"ٱلْعَظِيمِ","s":27,"a":26},{"t":"۩‏","s":27,"a":26},{"t":"۞","s":27,"a":27},{"t":"قَالَ","s":27,"a":27},{"t":"سَنَنظُرُ","s":27,"a":27}]},{"n":7,"words":[{"t":"أَصَدَقْتَ","s":27,"a":27},{"t":"أَمْ","s":27,"a":27},{"t":"كُنتَ","s":27,"a":27},{"t":"مِنَ","s":27,"a":27},{"t":"ٱلْكَـٰذِبِينَ","s":27,"a":27},{"t":"ٱذْهَب","s":27,"a":28},{"t":"بِّكِتَـٰبِى","s":27,"a":28},{"t":"هَـٰذَا","s":27,"a":28}]},{"n":8,"words":[{"t":"فَأَلْقِهْ","s":27,"a":28},{"t":"إِلَيْهِمْ","s":27,"a":28},{"t":"ثُمَّ","s":27,"a":28},{"t":"تَوَلَّ","s":27,"a":28},{"t":"عَنْهُمْ","s":27,"a":28},{"t":"فَٱنظُرْ","s":27,"a":28},{"t":"مَاذَا","s":27,"a":28},{"t":"يَرْجِعُونَ","s":27,"a":28},{"t":"قَالَتْ","s":27,"a":29},{"t":"يَـٰٓأَيُّهَا","s":27,"a":29}]},{"n":9,"words":[{"t":"ٱلْمَلَؤُا۟","s":27,"a":29},{"t":"إِنِّىٓ","s":27,"a":29},{"t":"أُلْقِىَ","s":27,"a":29},{"t":"إِلَىَّ","s":27,"a":29},{"t":"كِتَـٰبٌۭ","s":27,"a":29},{"t":"كَرِيمٌ","s":27,"a":29},{"t":"إِنَّهُۥ","s":27,"a":30},{"t":"مِن","s":27,"a":30},{"t":"سُلَيْمَـٰنَ","s":27,"a":30},{"t":"وَإِنَّهُۥ","s":27,"a":30},{"t":"بِسْمِ","s":27,"a":30}]},{"n":10,"words":[{"t":"ٱللَّهِ","s":27,"a":30},{"t":"ٱلرَّحْمَـٰنِ","s":27,"a":30},{"t":"ٱلرَّحِيمِ","s":27,"a":30},{"t":"أَلَّا","s":27,"a":31},{"t":"تَعْلُوا۟","s":27,"a":31},{"t":"عَلَىَّ","s":27,"a":31},{"t":"وَأْتُونِى","s":27,"a":31},{"t":"مُسْلِمِينَ","s":27,"a":31}]},{"n":11,"words":[{"t":"قَالَتْ","s":27,"a":32},{"t":"يَـٰٓأَيُّهَا","s":27,"a":32},{"t":"ٱلْمَلَؤُا۟","s":27,"a":32},{"t":"أَفْتُونِى","s":27,"a":32},{"t":"فِىٓ","s":27,"a":32},{"t":"أَمْرِى","s":27,"a":32},{"t":"مَا","s":27,"a":32},{"t":"كُنتُ","s":27,"a":32},{"t":"قَاطِعَةً","s":27,"a":32},{"t":"أَمْرًا","s":27,"a":32},{"t":"حَتَّىٰ","s":27,"a":32}]},{"n":12,"words":[{"t":"تَشْهَدُونِ","s":27,"a":32},{"t":"قَالُوا۟","s":27,"a":33},{"t":"نَحْنُ","s":27,"a":33},{"t":"أُو۟لُوا۟","s":27,"a":33},{"t":"قُوَّةٍۢ","s":27,"a":33},{"t":"وَأُو۟لُوا۟","s":27,"a":33},{"t":"بَأْسٍۢ","s":27,"a":33},{"t":"شَدِيدٍۢ","s":27,"a":33},{"t":"وَٱلْأَمْرُ","s":27,"a":33},{"t":"إِلَيْكِ","s":27,"a":33}]},{"n":13,"words":[{"t":"فَٱنظُرِى","s":27,"a":33},{"t":"مَاذَا","s":27,"a":33},{"t":"تَأْمُرِينَ","s":27,"a":33},{"t":"قَالَتْ","s":27,"a":34},{"t":"إِنَّ","s":27,"a":34},{"t":"ٱلْمُلُوكَ","s":27,"a":34},{"t":"إِذَا","s":27,"a":34},{"t":"دَخَلُوا۟","s":27,"a":34},{"t":"قَرْيَةً","s":27,"a":34}]},{"n":14,"words":[{"t":"أَفْسَدُوهَا","s":27,"a":34},{"t":"وَجَعَلُوٓا۟","s":27,"a":34},{"t":"أَعِزَّةَ","s":27,"a":34},{"t":"أَهْلِهَآ","s":27,"a":34},{"t":"أَذِلَّةًۭ","s":27,"a":34},{"t":"ۖ","s":27,"a":34},{"t":"وَكَذَٰلِكَ","s":27,"a":34},{"t":"يَفْعَلُونَ","s":27,"a":34}]},{"n":15,"words":[{"t":"وَإِنِّى","s":27,"a":35},{"t":"مُرْسِلَةٌ","s":27,"a":35},{"t":"إِلَيْهِم","s":27,"a":35},{"t":"بِهَدِيَّةٍۢ","s":27,"a":35},{"t":"فَنَاظِرَةٌۢ","s":27,"a":35},{"t":"بِمَ","s":27,"a":35},{"t":"يَرْجِعُ","s":27,"a":35},{"t":"ٱلْمُرْسَلُونَ","s":27,"a":35}]}]}