{"page":490,"juz":25,"lines":[{"n":1,"words":[{"t":"وَٱلَّذِى","s":43,"a":11},{"t":"نَزَّلَ","s":43,"a":11},{"t":"مِنَ","s":43,"a":11},{"t":"ٱلسَّمَآءِ","s":43,"a":11},{"t":"مَآءًۢ","s":43,"a":11},{"t":"بِقَدَرٍۢ","s":43,"a":11},{"t":"فَأَنشَرْنَا","s":43,"a":11},{"t":"بِهِۦ","s":43,"a":11},{"t":"بَلْدَةًۭ","s":43,"a":11},{"t":"مَّيْتًۭا","s":43,"a":11},{"t":"ۚ","s":43,"a":11}]},{"n":2,"words":[{"t":"كَذَٰلِكَ","s":43,"a":11},{"t":"تُخْرَجُونَ","s":43,"a":11},{"t":"وَٱلَّذِى","s":43,"a":12},{"t":"خَلَقَ","s":43,"a":12},{"t":"ٱلْأَزْوَٰجَ","s":43,"a":12},{"t":"كُلَّهَا","s":43,"a":12},{"t":"وَجَعَلَ","s":43,"a":12}]},{"n":3,"words":[{"t":"لَكُم","s":43,"a":12},{"t":"مِّنَ","s":43,"a":12},{"t":"ٱلْفُلْكِ","s":43,"a":12},{"t":"وَٱلْأَنْعَـٰمِ","s":43,"a":12},{"t":"مَا","s":43,"a":12},{"t":"تَرْكَبُونَ","s":43,"a":12},{"t":"لِتَسْتَوُۥا۟","s":43,"a":13},{"t":"عَلَىٰ","s":43,"a":13},{"t":"ظُهُورِهِۦ","s":43,"a":13}]},{"n":4,"words":[{"t":"ثُمَّ","s":43,"a":13},{"t":"تَذْكُرُوا۟","s":43,"a":13},{"t":"نِعْمَةَ","s":43,"a":13},{"t":"رَبِّكُمْ","s":43,"a":13},{"t":"إِذَا","s":43,"a":13},{"t":"ٱسْتَوَيْتُمْ","s":43,"a":13},{"t":"عَلَيْهِ","s":43,"a":13},{"t":"وَتَقُولُوا۟","s":43,"a":13},{"t":"سُبْحَـٰنَ","s":43,"a":13}]},{"n":5,"words":[{"t":"ٱلَّذِى","s":43,"a":13},{"t":"سَخَّرَ","s":43,"a":13},{"t":"لَنَا","s":43,"a":13},{"t":"هَـٰذَا","s":43,"a":13},{"t":"وَمَا","s":43,"a":13},{"t":"كُنَّا","s":43,"a":13},{"t":"لَهُۥ","s":43,"a":13},{"t":"مُقْرِنِينَ","s":43,"a":13},{"t":"وَإِنَّآ","s":43,"a":14},{"t":"إِلَىٰ","s":43,"a":14},{"t":"رَبِّنَا","s":43,"a":14}]},{"n":6,"words":[{"t":"لَمُنقَلِبُونَ","s":43,"a":14},{"t":"وَجَعَلُوا۟","s":43,"a":15},{"t":"لَهُۥ","s":43,"a":15},{"t":"مِنْ","s":43,"a":15},{"t":"عِبَادِهِۦ","s":43,"a":15},{"t":"جُزْءًا","s":43,"a":15},{"t":"ۚ","s":43,"a":15},{"t":"إِنَّ","s":43,"a":15},{"t":"ٱلْإِنسَـٰنَ","s":43,"a":15}]},{"n":7,"words":[{"t":"لَكَفُورٌۭ","s":43,"a":15},{"t":"مُّبِينٌ","s":43,"a":15},{"t":"أَمِ","s":43,"a":16},{"t":"ٱتَّخَذَ","s":43,"a":16},{"t":"مِمَّا","s":43,"a":16},{"t":"يَخْلُقُ","s":43,"a":16},{"t":"بَنَاتٍۢ","s":43,"a":16},{"t":"وَأَصْفَىٰكُم","s":43,"a":16}]},{"n":8,"words":[{"t":"بِٱلْبَنِينَ","s":43,"a":16},{"t":"وَإِذَا","s":43,"a":17},{"t":"بُشِّرَ","s":43,"a":17},{"t":"أَحَدُهُم","s":43,"a":17},{"t":"بِمَا","s":43,"a":17},{"t":"ضَرَبَ","s":43,"a":17},{"t":"لِلرَّحْمَـٰنِ","s":43,"a":17},{"t":"مَثَلًۭا","s":43,"a":17}]},{"n":9,"words":[{"t":"ظَلَّ","s":43,"a":17},{"t":"وَجْهُهُۥ","s":43,"a":17},{"t":"مُسْوَدًّۭا","s":43,"a":17},{"t":"وَهُوَ","s":43,"a":17},{"t":"كَظِيمٌ","s":43,"a":17},{"t":"أَوَمَن","s":43,"a":18},{"t":"يُنَشَّؤُا۟","s":43,"a":18},{"t":"فِى","s":43,"a":18}]},{"n":10,"words":[{"t":"ٱلْحِلْيَةِ","s":43,"a":18},{"t":"وَهُوَ","s":43,"a":18},{"t":"فِى","s":43,"a":18},{"t":"ٱلْخِصَامِ","s":43,"a":18},{"t":"غَيْرُ","s":43,"a":18},{"t":"مُبِينٍۢ","s":43,"a":18},{"t":"وَجَعَلُوا۟","s":43,"a":19},{"t":"ٱلْمَلَـٰٓئِكَةَ","s":43,"a":19}]},{"n":11,"words":[{"t":"ٱلَّذِينَ","s":43,"a":19},{"t":"هُمْ","s":43,"a":19},{"t":"عِبَـٰدُ","s":43,"a":19},{"t":"ٱلرَّحْمَـٰنِ","s":43,"a":19},{"t":"إِنَـٰثًا","s":43,"a":19},{"t":"ۚ","s":43,"a":19},{"t":"أَشَهِدُوا۟","s":43,"a":19},{"t":"خَلْقَهُمْ","s":43,"a":19},{"t":"ۚ","s":43,"a":19},{"t":"سَتُكْتَبُ","s":43,"a":19}]},{"n":12,"words":[{"t":"شَهَـٰدَتُهُمْ","s":43,"a":19},{"t":"وَيُسْـَٔلُونَ","s":43,"a":19},{"t":"وَقَالُوا۟","s":43,"a":20},{"t":"لَوْ","s":43,"a":20},{"t":"شَآءَ","s":43,"a":20},{"t":"ٱلرَّحْمَـٰنُ","s":43,"a":20},{"t":"مَا","s":43,"a":20},{"t":"عَبَدْنَـٰهُم","s":43,"a":20},{"t":"ۗ","s":43,"a":20}]},{"n":13,"words":[{"t":"مَّا","s":43,"a":20},{"t":"لَهُم","s":43,"a":20},{"t":"بِذَٰلِكَ","s":43,"a":20},{"t":"مِنْ","s":43,"a":20},{"t":"عِلْمٍ","s":43,"a":20},{"t":"ۖ","s":43,"a":20},{"t":"إِنْ","s":43,"a":20},{"t":"هُمْ","s":43,"a":20},{"t":"إِلَّا","s":43,"a":20},{"t":"يَخْرُصُونَ","s":43,"a":20},{"t":"أَمْ","s":43,"a":21},{"t":"ءَاتَيْنَـٰهُمْ","s":43,"a":21}]},{"n":14,"words":[{"t":"كِتَـٰبًۭا","s":43,"a":21},{"t":"مِّن","s":43,"a":21},{"t":"قَبْلِهِۦ","s":43,"a":21},{"t":"فَهُم","s":43,"a":21},{"t":"بِهِۦ","s":43,"a":21},{"t":"مُسْتَمْسِكُونَ","s":43,"a":21},{"t":"بَلْ","s":43,"a":22},{"t":"قَالُوٓا۟","s":43,"a":22}]},{"n":15,"words":[{"t":"إِنَّا","s":43,"a":22},{"t":"وَجَدْنَآ","s":43,"a":22},{"t":"ءَابَآءَنَا","s":43,"a":22},{"t":"عَلَىٰٓ","s":43,"a":22},{"t":"أُمَّةٍۢ","s":43,"a":22},{"t":"وَإِنَّا","s":43,"a":22},{"t":"عَلَىٰٓ","s":43,"a":22},{"t":"ءَاثَـٰرِهِم","s":43,"a":22},{"t":"مُّهْتَدُونَ","s":43,"a":22}]}]}