{"page":521,"juz":26,"lines":[{"n":1,"words":[{"t":"وَٱلسَّمَآءِ","s":51,"a":7},{"t":"ذَاتِ","s":51,"a":7},{"t":"ٱلْحُبُكِ","s":51,"a":7},{"t":"إِنَّكُمْ","s":51,"a":8},{"t":"لَفِى","s":51,"a":8},{"t":"قَوْلٍۢ","s":51,"a":8},{"t":"مُّخْتَلِفٍۢ","s":51,"a":8},{"t":"يُؤْفَكُ","s":51,"a":9},{"t":"عَنْهُ","s":51,"a":9},{"t":"مَنْ","s":51,"a":9}]},{"n":2,"words":[{"t":"أُفِكَ","s":51,"a":9},{"t":"قُتِلَ","s":51,"a":10},{"t":"ٱلْخَرَّٰصُونَ","s":51,"a":10},{"t":"ٱلَّذِينَ","s":51,"a":11},{"t":"هُمْ","s":51,"a":11},{"t":"فِى","s":51,"a":11},{"t":"غَمْرَةٍۢ","s":51,"a":11},{"t":"سَاهُونَ","s":51,"a":11}]},{"n":3,"words":[{"t":"يَسْـَٔلُونَ","s":51,"a":12},{"t":"أَيَّانَ","s":51,"a":12},{"t":"يَوْمُ","s":51,"a":12},{"t":"ٱلدِّينِ","s":51,"a":12},{"t":"يَوْمَ","s":51,"a":13},{"t":"هُمْ","s":51,"a":13},{"t":"عَلَى","s":51,"a":13},{"t":"ٱلنَّارِ","s":51,"a":13},{"t":"يُفْتَنُونَ","s":51,"a":13},{"t":"ذُوقُوا۟","s":51,"a":14}]},{"n":4,"words":[{"t":"فِتْنَتَكُمْ","s":51,"a":14},{"t":"هَـٰذَا","s":51,"a":14},{"t":"ٱلَّذِى","s":51,"a":14},{"t":"كُنتُم","s":51,"a":14},{"t":"بِهِۦ","s":51,"a":14},{"t":"تَسْتَعْجِلُونَ","s":51,"a":14},{"t":"إِنَّ","s":51,"a":15},{"t":"ٱلْمُتَّقِينَ","s":51,"a":15},{"t":"فِى","s":51,"a":15},{"t":"جَنَّـٰتٍۢ","s":51,"a":15}]},{"n":5,"words":[{"t":"وَعُيُونٍ","s":51,"a":15},{"t":"ءَاخِذِينَ","s":51,"a":16},{"t":"مَآ","s":51,"a":16},{"t":"ءَاتَىٰهُمْ","s":51,"a":16},{"t":"رَبُّهُمْ","s":51,"a":16},{"t":"ۚ","s":51,"a":16},{"t":"إِنَّهُمْ","s":51,"a":16},{"t":"كَانُوا۟","s":51,"a":16},{"t":"قَبْلَ","s":51,"a":16},{"t":"ذَٰلِكَ","s":51,"a":16},{"t":"مُحْسِنِينَ","s":51,"a":16}]},{"n":6,"words":[{"t":"كَانُوا۟","s":51,"a":17},{"t":"قَلِيلًۭا","s":51,"a":17},{"t":"مِّنَ","s":51,"a":17},{"t":"ٱلَّيْلِ","s":51,"a":17},{"t":"مَا","s":51,"a":17},{"t":"يَهْجَعُونَ","s":51,"a":17},{"t":"وَبِٱلْأَسْحَارِ","s":51,"a":18},{"t":"هُمْ","s":51,"a":18},{"t":"يَسْتَغْفِرُونَ","s":51,"a":18}]},{"n":7,"words":[{"t":"وَفِىٓ","s":51,"a":19},{"t":"أَمْوَٰلِهِمْ","s":51,"a":19},{"t":"حَقٌّۭ","s":51,"a":19},{"t":"لِّلسَّآئِلِ","s":51,"a":19},{"t":"وَٱلْمَحْرُومِ","s":51,"a":19},{"t":"وَفِى","s":51,"a":20},{"t":"ٱلْأَرْضِ","s":51,"a":20},{"t":"ءَايَـٰتٌۭ","s":51,"a":20}]},{"n":8,"words":[{"t":"لِّلْمُوقِنِينَ","s":51,"a":20},{"t":"وَفِىٓ","s":51,"a":21},{"t":"أَنفُسِكُمْ","s":51,"a":21},{"t":"ۚ","s":51,"a":21},{"t":"أَفَلَا","s":51,"a":21},{"t":"تُبْصِرُونَ","s":51,"a":21},{"t":"وَفِى","s":51,"a":22},{"t":"ٱلسَّمَآءِ","s":51,"a":22},{"t":"رِزْقُكُمْ","s":51,"a":22}]},{"n":9,"words":[{"t":"وَمَا","s":51,"a":22},{"t":"تُوعَدُونَ","s":51,"a":22},{"t":"فَوَرَبِّ","s":51,"a":23},{"t":"ٱلسَّمَآءِ","s":51,"a":23},{"t":"وَٱلْأَرْضِ","s":51,"a":23},{"t":"إِنَّهُۥ","s":51,"a":23},{"t":"لَحَقٌّۭ","s":51,"a":23},{"t":"مِّثْلَ","s":51,"a":23},{"t":"مَآ","s":51,"a":23},{"t":"أَنَّكُمْ","s":51,"a":23}]},{"n":10,"words":[{"t":"تَنطِقُونَ","s":51,"a":23},{"t":"هَلْ","s":51,"a":24},{"t":"أَتَىٰكَ","s":51,"a":24},{"t":"حَدِيثُ","s":51,"a":24},{"t":"ضَيْفِ","s":51,"a":24},{"t":"إِبْرَٰهِيمَ","s":51,"a":24},{"t":"ٱلْمُكْرَمِينَ","s":51,"a":24}]},{"n":11,"words":[{"t":"إِذْ","s":51,"a":25},{"t":"دَخَلُوا۟","s":51,"a":25},{"t":"عَلَيْهِ","s":51,"a":25},{"t":"فَقَالُوا۟","s":51,"a":25},{"t":"سَلَـٰمًۭا","s":51,"a":25},{"t":"ۖ","s":51,"a":25},{"t":"قَالَ","s":51,"a":25},{"t":"سَلَـٰمٌۭ","s":51,"a":25},{"t":"قَوْمٌۭ","s":51,"a":25},{"t":"مُّنكَرُونَ","s":51,"a":25},{"t":"فَرَاغَ","s":51,"a":26},{"t":"إِلَىٰٓ","s":51,"a":26}]},{"n":12,"words":[{"t":"أَهْلِهِۦ","s":51,"a":26},{"t":"فَجَآءَ","s":51,"a":26},{"t":"بِعِجْلٍۢ","s":51,"a":26},{"t":"سَمِينٍۢ","s":51,"a":26},{"t":"فَقَرَّبَهُۥٓ","s":51,"a":27},{"t":"إِلَيْهِمْ","s":51,"a":27},{"t":"قَالَ","s":51,"a":27},{"t":"أَلَا","s":51,"a":27},{"t":"تَأْكُلُونَ","s":51,"a":27}]},{"n":13,"words":[{"t":"فَأَوْجَسَ","s":51,"a":28},{"t":"مِنْهُمْ","s":51,"a":28},{"t":"خِيفَةًۭ","s":51,"a":28},{"t":"ۖ","s":51,"a":28},{"t":"قَالُوا۟","s":51,"a":28},{"t":"لَا","s":51,"a":28},{"t":"تَخَفْ","s":51,"a":28},{"t":"ۖ","s":51,"a":28},{"t":"وَبَشَّرُوهُ","s":51,"a":28},{"t":"بِغُلَـٰمٍ","s":51,"a":28},{"t":"عَلِيمٍۢ","s":51,"a":28}]},{"n":14,"words":[{"t":"فَأَقْبَلَتِ","s":51,"a":29},{"t":"ٱمْرَأَتُهُۥ","s":51,"a":29},{"t":"فِى","s":51,"a":29},{"t":"صَرَّةٍۢ","s":51,"a":29},{"t":"فَصَكَّتْ","s":51,"a":29},{"t":"وَجْهَهَا","s":51,"a":29},{"t":"وَقَالَتْ","s":51,"a":29},{"t":"عَجُوزٌ","s":51,"a":29},{"t":"عَقِيمٌۭ","s":51,"a":29}]},{"n":15,"words":[{"t":"قَالُوا۟","s":51,"a":30},{"t":"كَذَٰلِكِ","s":51,"a":30},{"t":"قَالَ","s":51,"a":30},{"t":"رَبُّكِ","s":51,"a":30},{"t":"ۖ","s":51,"a":30},{"t":"إِنَّهُۥ","s":51,"a":30},{"t":"هُوَ","s":51,"a":30},{"t":"ٱلْحَكِيمُ","s":51,"a":30},{"t":"ٱلْعَلِيمُ","s":51,"a":30}]}]}