{"page":599,"juz":30,"lines":[{"n":1,"words":[{"t":"جَزَآؤُهُمْ","s":98,"a":8},{"t":"عِندَ","s":98,"a":8},{"t":"رَبِّهِمْ","s":98,"a":8},{"t":"جَنَّـٰتُ","s":98,"a":8},{"t":"عَدْنٍۢ","s":98,"a":8},{"t":"تَجْرِى","s":98,"a":8},{"t":"مِن","s":98,"a":8},{"t":"تَحْتِهَا","s":98,"a":8},{"t":"ٱلْأَنْهَـٰرُ","s":98,"a":8},{"t":"خَـٰلِدِينَ","s":98,"a":8}]},{"n":2,"words":[{"t":"فِيهَآ","s":98,"a":8},{"t":"أَبَدًۭا","s":98,"a":8},{"t":"ۖ","s":98,"a":8},{"t":"رَّضِىَ","s":98,"a":8},{"t":"ٱللَّهُ","s":98,"a":8},{"t":"عَنْهُمْ","s":98,"a":8},{"t":"وَرَضُوا۟","s":98,"a":8},{"t":"عَنْهُ","s":98,"a":8},{"t":"ۚ","s":98,"a":8},{"t":"ذَٰلِكَ","s":98,"a":8},{"t":"لِمَنْ","s":98,"a":8},{"t":"خَشِىَ","s":98,"a":8},{"t":"رَبَّهُۥ","s":98,"a":8}]},{"n":3,"words":[]},{"n":4,"words":[]},{"n":5,"words":[{"t":"إِذَا","s":99,"a":1},{"t":"زُلْزِلَتِ","s":99,"a":1},{"t":"ٱلْأَرْضُ","s":99,"a":1},{"t":"زِلْزَالَهَا","s":99,"a":1},{"t":"وَأَخْرَجَتِ","s":99,"a":2},{"t":"ٱلْأَرْضُ","s":99,"a":2},{"t":"أَثْقَالَهَا","s":99,"a":2}]},{"n":6,"words":[{"t":"وَقَالَ","s":99,"a":3},{"t":"ٱلْإِنسَـٰنُ","s":99,"a":3},{"t":"مَا","s":99,"a":3},{"t":"لَهَا","s":99,"a":3},{"t":"يَوْمَئِذٍۢ","s":99,"a":4},{"t":"تُحَدِّثُ","s":99,"a":4},{"t":"أَخْبَارَهَا","s":99,"a":4}]},{"n":7,"words":[{"t":"بِأَنَّ","s":99,"a":5},{"t":"رَبَّكَ","s":99,"a":5},{"t":"أَوْحَىٰ","s":99,"a":5},{"t":"لَهَا","s":99,"a":5},{"t":"يَوْمَئِذٍۢ","s":99,"a":6},{"t":"يَصْدُرُ","s":99,"a":6},{"t":"ٱلنَّاسُ","s":99,"a":6},{"t":"أَشْتَاتًۭا","s":99,"a":6}]},{"n":8,"words":[{"t":"لِّيُرَوْا۟","s":99,"a":6},{"t":"أَعْمَـٰلَهُمْ","s":99,"a":6},{"t":"فَمَن","s":99,"a":7},{"t":"يَعْمَلْ","s":99,"a":7},{"t":"مِثْقَالَ","s":99,"a":7},{"t":"ذَرَّةٍ","s":99,"a":7},{"t":"خَيْرًۭا","s":99,"a":7}]},{"n":9,"words":[{"t":"يَرَهُۥ","s":99,"a":7},{"t":"وَمَن","s":99,"a":8},{"t":"يَعْمَلْ","s":99,"a":8},{"t":"مِثْقَالَ","s":99,"a":8},{"t":"ذَرَّةٍۢ","s":99,"a":8},{"t":"شَرًّۭا","s":99,"a":8},{"t":"يَرَهُۥ","s":99,"a":8}]},{"n":10,"words":[]},{"n":11,"words":[]},{"n":12,"words":[{"t":"وَٱلْعَـٰدِيَـٰتِ","s":100,"a":1},{"t":"ضَبْحًۭا","s":100,"a":1},{"t":"فَٱلْمُورِيَـٰتِ","s":100,"a":2},{"t":"قَدْحًۭا","s":100,"a":2},{"t":"فَٱلْمُغِيرَٰتِ","s":100,"a":3},{"t":"صُبْحًۭا","s":100,"a":3}]},{"n":13,"words":[{"t":"فَأَثَرْنَ","s":100,"a":4},{"t":"بِهِۦ","s":100,"a":4},{"t":"نَقْعًۭا","s":100,"a":4},{"t":"فَوَسَطْنَ","s":100,"a":5},{"t":"بِهِۦ","s":100,"a":5},{"t":"جَمْعًا","s":100,"a":5},{"t":"إِنَّ","s":100,"a":6},{"t":"ٱلْإِنسَـٰنَ","s":100,"a":6}]},{"n":14,"words":[{"t":"لِرَبِّهِۦ","s":100,"a":6},{"t":"لَكَنُودٌۭ","s":100,"a":6},{"t":"وَإِنَّهُۥ","s":100,"a":7},{"t":"عَلَىٰ","s":100,"a":7},{"t":"ذَٰلِكَ","s":100,"a":7},{"t":"لَشَهِيدٌۭ","s":100,"a":7},{"t":"وَإِنَّهُۥ","s":100,"a":8},{"t":"لِحُبِّ","s":100,"a":8}]},{"n":15,"words":[{"t":"ٱلْخَيْرِ","s":100,"a":8},{"t":"لَشَدِيدٌ","s":100,"a":8},{"t":"۞","s":100,"a":9},{"t":"أَفَلَا","s":100,"a":9},{"t":"يَعْلَمُ","s":100,"a":9},{"t":"إِذَا","s":100,"a":9},{"t":"بُعْثِرَ","s":100,"a":9},{"t":"مَا","s":100,"a":9},{"t":"فِى","s":100,"a":9},{"t":"ٱلْقُبُورِ","s":100,"a":9}]}]}