{"page":61,"juz":3,"lines":[{"n":1,"words":[{"t":"قُلْ","s":3,"a":84},{"t":"ءَامَنَّا","s":3,"a":84},{"t":"بِٱللَّهِ","s":3,"a":84},{"t":"وَمَآ","s":3,"a":84},{"t":"أُنزِلَ","s":3,"a":84},{"t":"عَلَيْنَا","s":3,"a":84},{"t":"وَمَآ","s":3,"a":84},{"t":"أُنزِلَ","s":3,"a":84},{"t":"عَلَىٰٓ","s":3,"a":84},{"t":"إِبْرَٰهِيمَ","s":3,"a":84}]},{"n":2,"words":[{"t":"وَإِسْمَـٰعِيلَ","s":3,"a":84},{"t":"وَإِسْحَـٰقَ","s":3,"a":84},{"t":"وَيَعْقُوبَ","s":3,"a":84},{"t":"وَٱلْأَسْبَاطِ","s":3,"a":84},{"t":"وَمَآ","s":3,"a":84},{"t":"أُوتِىَ","s":3,"a":84}]},{"n":3,"words":[{"t":"مُوسَىٰ","s":3,"a":84},{"t":"وَعِيسَىٰ","s":3,"a":84},{"t":"وَٱلنَّبِيُّونَ","s":3,"a":84},{"t":"مِن","s":3,"a":84},{"t":"رَّبِّهِمْ","s":3,"a":84},{"t":"لَا","s":3,"a":84},{"t":"نُفَرِّقُ","s":3,"a":84},{"t":"بَيْنَ","s":3,"a":84},{"t":"أَحَدٍۢ","s":3,"a":84}]},{"n":4,"words":[{"t":"مِّنْهُمْ","s":3,"a":84},{"t":"وَنَحْنُ","s":3,"a":84},{"t":"لَهُۥ","s":3,"a":84},{"t":"مُسْلِمُونَ","s":3,"a":84},{"t":"وَمَن","s":3,"a":85},{"t":"يَبْتَغِ","s":3,"a":85},{"t":"غَيْرَ","s":3,"a":85},{"t":"ٱلْإِسْلَـٰمِ","s":3,"a":85}]},{"n":5,"words":[{"t":"دِينًۭا","s":3,"a":85},{"t":"فَلَن","s":3,"a":85},{"t":"يُقْبَلَ","s":3,"a":85},{"t":"مِنْهُ","s":3,"a":85},{"t":"وَهُوَ","s":3,"a":85},{"t":"فِى","s":3,"a":85},{"t":"ٱلْـَٔاخِرَةِ","s":3,"a":85},{"t":"مِنَ","s":3,"a":85},{"t":"ٱلْخَـٰسِرِينَ","s":3,"a":85}]},{"n":6,"words":[{"t":"كَيْفَ","s":3,"a":86},{"t":"يَهْدِى","s":3,"a":86},{"t":"ٱللَّهُ","s":3,"a":86},{"t":"قَوْمًۭا","s":3,"a":86},{"t":"كَفَرُوا۟","s":3,"a":86},{"t":"بَعْدَ","s":3,"a":86},{"t":"إِيمَـٰنِهِمْ","s":3,"a":86},{"t":"وَشَهِدُوٓا۟","s":3,"a":86}]},{"n":7,"words":[{"t":"أَنَّ","s":3,"a":86},{"t":"ٱلرَّسُولَ","s":3,"a":86},{"t":"حَقٌّۭ","s":3,"a":86},{"t":"وَجَآءَهُمُ","s":3,"a":86},{"t":"ٱلْبَيِّنَـٰتُ","s":3,"a":86},{"t":"ۚ","s":3,"a":86},{"t":"وَٱللَّهُ","s":3,"a":86},{"t":"لَا","s":3,"a":86},{"t":"يَهْدِى","s":3,"a":86},{"t":"ٱلْقَوْمَ","s":3,"a":86}]},{"n":8,"words":[{"t":"ٱلظَّـٰلِمِينَ","s":3,"a":86},{"t":"أُو۟لَـٰٓئِكَ","s":3,"a":87},{"t":"جَزَآؤُهُمْ","s":3,"a":87},{"t":"أَنَّ","s":3,"a":87},{"t":"عَلَيْهِمْ","s":3,"a":87},{"t":"لَعْنَةَ","s":3,"a":87},{"t":"ٱللَّهِ","s":3,"a":87}]},{"n":9,"words":[{"t":"وَٱلْمَلَـٰٓئِكَةِ","s":3,"a":87},{"t":"وَٱلنَّاسِ","s":3,"a":87},{"t":"أَجْمَعِينَ","s":3,"a":87},{"t":"خَـٰلِدِينَ","s":3,"a":88},{"t":"فِيهَا","s":3,"a":88},{"t":"لَا","s":3,"a":88},{"t":"يُخَفَّفُ","s":3,"a":88}]},{"n":10,"words":[{"t":"عَنْهُمُ","s":3,"a":88},{"t":"ٱلْعَذَابُ","s":3,"a":88},{"t":"وَلَا","s":3,"a":88},{"t":"هُمْ","s":3,"a":88},{"t":"يُنظَرُونَ","s":3,"a":88},{"t":"إِلَّا","s":3,"a":89},{"t":"ٱلَّذِينَ","s":3,"a":89},{"t":"تَابُوا۟","s":3,"a":89},{"t":"مِنۢ","s":3,"a":89}]},{"n":11,"words":[{"t":"بَعْدِ","s":3,"a":89},{"t":"ذَٰلِكَ","s":3,"a":89},{"t":"وَأَصْلَحُوا۟","s":3,"a":89},{"t":"فَإِنَّ","s":3,"a":89},{"t":"ٱللَّهَ","s":3,"a":89},{"t":"غَفُورٌۭ","s":3,"a":89},{"t":"رَّحِيمٌ","s":3,"a":89},{"t":"إِنَّ","s":3,"a":90},{"t":"ٱلَّذِينَ","s":3,"a":90}]},{"n":12,"words":[{"t":"كَفَرُوا۟","s":3,"a":90},{"t":"بَعْدَ","s":3,"a":90},{"t":"إِيمَـٰنِهِمْ","s":3,"a":90},{"t":"ثُمَّ","s":3,"a":90},{"t":"ٱزْدَادُوا۟","s":3,"a":90},{"t":"كُفْرًۭا","s":3,"a":90},{"t":"لَّن","s":3,"a":90},{"t":"تُقْبَلَ","s":3,"a":90},{"t":"تَوْبَتُهُمْ","s":3,"a":90}]},{"n":13,"words":[{"t":"وَأُو۟لَـٰٓئِكَ","s":3,"a":90},{"t":"هُمُ","s":3,"a":90},{"t":"ٱلضَّآلُّونَ","s":3,"a":90},{"t":"إِنَّ","s":3,"a":91},{"t":"ٱلَّذِينَ","s":3,"a":91},{"t":"كَفَرُوا۟","s":3,"a":91},{"t":"وَمَاتُوا۟","s":3,"a":91},{"t":"وَهُمْ","s":3,"a":91}]},{"n":14,"words":[{"t":"كُفَّارٌۭ","s":3,"a":91},{"t":"فَلَن","s":3,"a":91},{"t":"يُقْبَلَ","s":3,"a":91},{"t":"مِنْ","s":3,"a":91},{"t":"أَحَدِهِم","s":3,"a":91},{"t":"مِّلْءُ","s":3,"a":91},{"t":"ٱلْأَرْضِ","s":3,"a":91},{"t":"ذَهَبًۭا","s":3,"a":91},{"t":"وَلَوِ","s":3,"a":91}]},{"n":15,"words":[{"t":"ٱفْتَدَىٰ","s":3,"a":91},{"t":"بِهِۦٓ","s":3,"a":91},{"t":"ۗ","s":3,"a":91},{"t":"أُو۟لَـٰٓئِكَ","s":3,"a":91},{"t":"لَهُمْ","s":3,"a":91},{"t":"عَذَابٌ","s":3,"a":91},{"t":"أَلِيمٌۭ","s":3,"a":91},{"t":"وَمَا","s":3,"a":91},{"t":"لَهُم","s":3,"a":91},{"t":"مِّن","s":3,"a":91},{"t":"نَّـٰصِرِينَ","s":3,"a":91}]}]}