{"page":74,"juz":4,"lines":[{"n":1,"words":[{"t":"لَّقَدْ","s":3,"a":181},{"t":"سَمِعَ","s":3,"a":181},{"t":"ٱللَّهُ","s":3,"a":181},{"t":"قَوْلَ","s":3,"a":181},{"t":"ٱلَّذِينَ","s":3,"a":181},{"t":"قَالُوٓا۟","s":3,"a":181},{"t":"إِنَّ","s":3,"a":181},{"t":"ٱللَّهَ","s":3,"a":181},{"t":"فَقِيرٌۭ","s":3,"a":181},{"t":"وَنَحْنُ","s":3,"a":181},{"t":"أَغْنِيَآءُ","s":3,"a":181},{"t":"ۘ","s":3,"a":181}]},{"n":2,"words":[{"t":"سَنَكْتُبُ","s":3,"a":181},{"t":"مَا","s":3,"a":181},{"t":"قَالُوا۟","s":3,"a":181},{"t":"وَقَتْلَهُمُ","s":3,"a":181},{"t":"ٱلْأَنۢبِيَآءَ","s":3,"a":181},{"t":"بِغَيْرِ","s":3,"a":181},{"t":"حَقٍّۢ","s":3,"a":181},{"t":"وَنَقُولُ","s":3,"a":181}]},{"n":3,"words":[{"t":"ذُوقُوا۟","s":3,"a":181},{"t":"عَذَابَ","s":3,"a":181},{"t":"ٱلْحَرِيقِ","s":3,"a":181},{"t":"ذَٰلِكَ","s":3,"a":182},{"t":"بِمَا","s":3,"a":182},{"t":"قَدَّمَتْ","s":3,"a":182},{"t":"أَيْدِيكُمْ","s":3,"a":182}]},{"n":4,"words":[{"t":"وَأَنَّ","s":3,"a":182},{"t":"ٱللَّهَ","s":3,"a":182},{"t":"لَيْسَ","s":3,"a":182},{"t":"بِظَلَّامٍۢ","s":3,"a":182},{"t":"لِّلْعَبِيدِ","s":3,"a":182},{"t":"ٱلَّذِينَ","s":3,"a":183},{"t":"قَالُوٓا۟","s":3,"a":183},{"t":"إِنَّ","s":3,"a":183}]},{"n":5,"words":[{"t":"ٱللَّهَ","s":3,"a":183},{"t":"عَهِدَ","s":3,"a":183},{"t":"إِلَيْنَآ","s":3,"a":183},{"t":"أَلَّا","s":3,"a":183},{"t":"نُؤْمِنَ","s":3,"a":183},{"t":"لِرَسُولٍ","s":3,"a":183},{"t":"حَتَّىٰ","s":3,"a":183},{"t":"يَأْتِيَنَا","s":3,"a":183},{"t":"بِقُرْبَانٍۢ","s":3,"a":183}]},{"n":6,"words":[{"t":"تَأْكُلُهُ","s":3,"a":183},{"t":"ٱلنَّارُ","s":3,"a":183},{"t":"ۗ","s":3,"a":183},{"t":"قُلْ","s":3,"a":183},{"t":"قَدْ","s":3,"a":183},{"t":"جَآءَكُمْ","s":3,"a":183},{"t":"رُسُلٌۭ","s":3,"a":183},{"t":"مِّن","s":3,"a":183},{"t":"قَبْلِى","s":3,"a":183},{"t":"بِٱلْبَيِّنَـٰتِ","s":3,"a":183}]},{"n":7,"words":[{"t":"وَبِٱلَّذِى","s":3,"a":183},{"t":"قُلْتُمْ","s":3,"a":183},{"t":"فَلِمَ","s":3,"a":183},{"t":"قَتَلْتُمُوهُمْ","s":3,"a":183},{"t":"إِن","s":3,"a":183},{"t":"كُنتُمْ","s":3,"a":183},{"t":"صَـٰدِقِينَ","s":3,"a":183}]},{"n":8,"words":[{"t":"فَإِن","s":3,"a":184},{"t":"كَذَّبُوكَ","s":3,"a":184},{"t":"فَقَدْ","s":3,"a":184},{"t":"كُذِّبَ","s":3,"a":184},{"t":"رُسُلٌۭ","s":3,"a":184},{"t":"مِّن","s":3,"a":184},{"t":"قَبْلِكَ","s":3,"a":184},{"t":"جَآءُو","s":3,"a":184},{"t":"بِٱلْبَيِّنَـٰتِ","s":3,"a":184}]},{"n":9,"words":[{"t":"وَٱلزُّبُرِ","s":3,"a":184},{"t":"وَٱلْكِتَـٰبِ","s":3,"a":184},{"t":"ٱلْمُنِيرِ","s":3,"a":184},{"t":"كُلُّ","s":3,"a":185},{"t":"نَفْسٍۢ","s":3,"a":185},{"t":"ذَآئِقَةُ","s":3,"a":185},{"t":"ٱلْمَوْتِ","s":3,"a":185},{"t":"ۗ","s":3,"a":185}]},{"n":10,"words":[{"t":"وَإِنَّمَا","s":3,"a":185},{"t":"تُوَفَّوْنَ","s":3,"a":185},{"t":"أُجُورَكُمْ","s":3,"a":185},{"t":"يَوْمَ","s":3,"a":185},{"t":"ٱلْقِيَـٰمَةِ","s":3,"a":185},{"t":"ۖ","s":3,"a":185},{"t":"فَمَن","s":3,"a":185},{"t":"زُحْزِحَ","s":3,"a":185}]},{"n":11,"words":[{"t":"عَنِ","s":3,"a":185},{"t":"ٱلنَّارِ","s":3,"a":185},{"t":"وَأُدْخِلَ","s":3,"a":185},{"t":"ٱلْجَنَّةَ","s":3,"a":185},{"t":"فَقَدْ","s":3,"a":185},{"t":"فَازَ","s":3,"a":185},{"t":"ۗ","s":3,"a":185},{"t":"وَمَا","s":3,"a":185},{"t":"ٱلْحَيَوٰةُ","s":3,"a":185},{"t":"ٱلدُّنْيَآ","s":3,"a":185}]},{"n":12,"words":[{"t":"إِلَّا","s":3,"a":185},{"t":"مَتَـٰعُ","s":3,"a":185},{"t":"ٱلْغُرُورِ","s":3,"a":185},{"t":"۞","s":3,"a":186},{"t":"لَتُبْلَوُنَّ","s":3,"a":186},{"t":"فِىٓ","s":3,"a":186},{"t":"أَمْوَٰلِكُمْ","s":3,"a":186}]},{"n":13,"words":[{"t":"وَأَنفُسِكُمْ","s":3,"a":186},{"t":"وَلَتَسْمَعُنَّ","s":3,"a":186},{"t":"مِنَ","s":3,"a":186},{"t":"ٱلَّذِينَ","s":3,"a":186},{"t":"أُوتُوا۟","s":3,"a":186},{"t":"ٱلْكِتَـٰبَ","s":3,"a":186}]},{"n":14,"words":[{"t":"مِن","s":3,"a":186},{"t":"قَبْلِكُمْ","s":3,"a":186},{"t":"وَمِنَ","s":3,"a":186},{"t":"ٱلَّذِينَ","s":3,"a":186},{"t":"أَشْرَكُوٓا۟","s":3,"a":186},{"t":"أَذًۭى","s":3,"a":186},{"t":"كَثِيرًۭا","s":3,"a":186},{"t":"ۚ","s":3,"a":186}]},{"n":15,"words":[{"t":"وَإِن","s":3,"a":186},{"t":"تَصْبِرُوا۟","s":3,"a":186},{"t":"وَتَتَّقُوا۟","s":3,"a":186},{"t":"فَإِنَّ","s":3,"a":186},{"t":"ذَٰلِكَ","s":3,"a":186},{"t":"مِنْ","s":3,"a":186},{"t":"عَزْمِ","s":3,"a":186},{"t":"ٱلْأُمُورِ","s":3,"a":186}]}]}